Workbook

Sheet 1. P&L Summary
A1: AURUM — MASTER P&L SUMMARY | H1: → Summary | O1: → Summary
A2: Revenue & cost matrix by Physical vs AGP. Annualized base case. All USD.
A4: REVENUE
A5: Revenue Stream | B5: Physical | C5: AGP | D5: Total | E5: % of Rev | F5: Type
A6: — Premium revenue
A7: Premium — Founders Plan | B7: ='13. Founders — Aggregate'!G11 -> 679250 | C7: 0 | D7: =B7+C7 -> 679250 | E7: =IFERROR(D7/$D$18,0) -> 0.21967851 | F7: Variable
A8: Premium — AGP Plan | B8: 0 | C8: ='16. AGP — Math'!G27+'18. AGP Sign-up — Math'!H12 -> 2310188.1 | D8: =B8+C8 -> 2310188.1 | E8: =IFERROR(D8/$D$18,0) -> 0.74714565 | F8: Variable
A9: Premium — Basic | B9: =('17. AGP Sign-up — Inputs'!B16*(1-'17. AGP Sign-up — Inputs'!B17))*'4. Pricing Levers'!B27*'4. Pricing Levers'!B28*'4. Pricing Levers'!B12 -> 8312.5 | C9: 0 | D9: =B9+C9 -> 8312.5 | E9: =IFERROR(D9/$D$18,0) -> 0.0026883733 | F9: Variable
A10: Subtotal: Premium revenue | B10: =SUM(B7:B9) -> 687562.5 | C10: =SUM(C7:C9) -> 2310188.1 | D10: =B10+C10 -> 2997750.6 | E10: =IFERROR(D10/$D$18,0) -> 0.96951254
A11: — Other revenue
A12: Storage fees | B12: ='13. Founders — Aggregate'!C11*'11. Founders — Inputs'!B6*'4. Pricing Levers'!B15 -> 7120 | C12: ='16. AGP — Math'!H27 -> 51718.8 | D12: =B12+C12 -> 58838.8 | E12: =IFERROR(D12/$D$18,0) -> 0.019029253 | F12: Recurring
A13: Sell-back spread | B13: ='11. Founders — Inputs'!B5*('11. Founders — Inputs'!B6*0.9+'11. Founders — Inputs'!B7*0.1)*0.05*'4. Pricing Levers'!B18 -> 1500 | C13: 0 | D13: =B13+C13 -> 1500 | E13: =IFERROR(D13/$D$18,0) -> 0.00048512 | F13: Variable
A14: Subscription (AGP+) | B14: 0 | C14: ='16. AGP — Math'!D16*'4. Pricing Levers'!B20*'4. Pricing Levers'!B19*12 -> 31794 | D14: =B14+C14 -> 31794 | E14: =IFERROR(D14/$D$18,0) -> 0.010282604 | F14: Recurring
A15: Insurance add-on | B15: ='11. Founders — Inputs'!B5*('11. Founders — Inputs'!B6*0.9+'11. Founders — Inputs'!B7*0.1)/2*'4. Pricing Levers'!B21*'4. Pricing Levers'!B22 -> 480 | C15: ='16. AGP — Math'!F27/2*'4. Pricing Levers'!B21*'4. Pricing Levers'!B22 -> 1655.0016 | D15: =B15+C15 -> 2135.0016 | E15: =IFERROR(D15/$D$18,0) -> 0.00069048799 | F15: Recurring
A16: Other revenue | B16: 0 | C16: 0 | D16: =B16+C16 -> 0 | E16: =IFERROR(D16/$D$18,0) -> 0 | F16: Variable
A17: Subtotal: Other revenue | B17: =SUM(B12:B16) -> 9100 | C17: =SUM(C12:C16) -> 85167.802 | D17: =B17+C17 -> 94267.802 | E17: =IFERROR(D17/$D$18,0) -> 0.030487464
A18: TOTAL REVENUE | B18: =B10+B17 -> 696662.5 | C18: =C10+C17 -> 2395356 | D18: =B18+C18 -> 3092018.5 | E18: 100%
A21: COSTS
A22: Cost Center | B22: Physical | C22: AGP | D22: Total | E22: % of Cost | F22: Direct/Indirect
A23: — DIRECT COSTS
A24: Wholesale (COGS) | B24: ='11. Founders — Inputs'!B5*('11. Founders — Inputs'!B6*0.9+'11. Founders — Inputs'!B7*0.1)*'4. Pricing Levers'!B23 -> 60000 | C24: ='16. AGP — Math'!F27*'4. Pricing Levers'!B23 -> 206875.2 | D24: =B24+C24 -> 266875.2 | E24: =IFERROR(D24/$D$42,0) -> 0.50751203 | F24: Direct
A25: Founder Savings discount | B25: ='13. Founders — Aggregate'!E11 -> 35204.25 | C25: 0 | D25: =B25+C25 -> 35204.25 | E25: =IFERROR(D25/$D$42,0) -> 0.066947323 | F25: Direct
A26: KYC/AML per new customer | B26: ='11. Founders — Inputs'!B5*'4. Pricing Levers'!B24 -> 30000 | C26: ='16. AGP — Math'!D16*'4. Pricing Levers'!B24 -> 56775 | D26: =B26+C26 -> 86775 | E26: =IFERROR(D26/$D$42,0) -> 0.16501854 | F26: Direct
A27: Storage pass-through | B27: ='11. Founders — Inputs'!B5*('11. Founders — Inputs'!B6*0.9+'11. Founders — Inputs'!B7*0.1)*'4. Pricing Levers'!B17 -> 15000 | C27: ='16. AGP — Math'!F27*'4. Pricing Levers'!B17 -> 51718.8 | D27: =B27+C27 -> 66718.8 | E27: =IFERROR(D27/$D$42,0) -> 0.12687801 | F27: Direct
A28: Other direct cost | B28: 0 | C28: 0 | D28: =B28+C28 -> 0 | E28: =IFERROR(D28/$D$42,0) -> 0 | F28: Direct
A29: Subtotal: Direct costs | B29: =SUM(B24:B28) -> 140204.25 | C29: =SUM(C24:C28) -> 315369 | D29: =B29+C29 -> 455573.25 | E29: =IFERROR(D29/$D$42,0) -> 0.8663559
A30: — INDIRECT COSTS
A31: Marketing — Promotion (parent)
A32: · Sign-up Gifts (sub) | B32: 0 | C32: ='18. AGP Sign-up — Math'!E12 -> 166250 | D32: =B32+C32 -> 166250 | E32: =IFERROR(D32/$D$42,0) -> 0.3161548 | F32: Indirect
A33: · Founders campaign mktg (sub) | B33: 0 | C33: 0 | D33: =B33+C33 -> 0 | E33: =IFERROR(D33/$D$42,0) -> 0 | F33: Indirect
A34: · AGP acquisition mktg (sub) | B34: 0 | C34: ='15. AGP — Inputs'!B27*12 -> 120000 | D34: =B34+C34 -> 120000 | E34: =IFERROR(D34/$D$42,0) -> 0.22820196 | F34: Indirect
A35: · AGP Sign-up campaign mktg (sub) | B35: 0 | C35: ='17. AGP Sign-up — Inputs'!B19 -> 50000 | D35: =B35+C35 -> 50000 | E35: =IFERROR(D35/$D$42,0) -> 0.095084149 | F35: Indirect
A36: Subtotal: Marketing — Promotion | B36: =SUM(B32:B35) -> 0 | C36: =SUM(C32:C35) -> 336250 | D36: =B36+C36 -> 336250 | E36: =IFERROR(D36/$D$42,0) -> 0.63944091
A37: Marketing — Brand (always-on) | B37: ='4. Pricing Levers'!B34*12*0.5 -> 30000 | C37: ='4. Pricing Levers'!B34*12*0.5 -> 30000 | D37: =B37+C37 -> 60000 | E37: =IFERROR(D37/$D$42,0) -> 0.11410098 | F37: Indirect
A38: Compliance (PSPM, PIPA, audit) | B38: ='4. Pricing Levers'!B31*12*0.5 -> 16800 | C38: ='4. Pricing Levers'!B31*12*0.5 -> 16800 | D38: =B38+C38 -> 33600 | E38: =IFERROR(D38/$D$42,0) -> 0.063896548 | F38: Indirect
A39: Tech platform | B39: ='4. Pricing Levers'!B32*12*0.5 -> 9000 | C39: ='4. Pricing Levers'!B32*12*0.5 -> 9000 | D39: =B39+C39 -> 18000 | E39: =IFERROR(D39/$D$42,0) -> 0.034230294 | F39: Indirect
A40: Personnel | B40: ='4. Pricing Levers'!B33*12*0.5 -> 39000 | C40: ='4. Pricing Levers'!B33*12*0.5 -> 39000 | D40: =B40+C40 -> 78000 | E40: =IFERROR(D40/$D$42,0) -> 0.14833127 | F40: Indirect
A41: Other indirect cost | B41: 0 | C41: 0 | D41: =B41+C41 -> 0 | E41: =IFERROR(D41/$D$42,0) -> 0 | F41: Indirect
A42: Subtotal: Indirect costs (Mktg-Promo + others) | B42: =B36+SUM(B37:B41) -> 94800 | C42: =C36+SUM(C37:C41) -> 431050 | D42: =B42+C42 -> 525850 | E42: =IFERROR(D42/$D$43,0) -> 0.53580349
A43: TOTAL COSTS | B43: =B29+B42 -> 235004.25 | C43: =C29+C42 -> 746419 | D43: =B43+C43 -> 981423.25 | E43: 100%
A46: GROSS MARGIN BY PRODUCT LINE
A47: Metric | B47: Physical | C47: AGP | D47: Combined | E47: % of Total | F47: Note
A48: Revenue | B48: =B18 -> 696662.5 | C48: =C18 -> 2395356 | D48: =D18 -> 3092018.5 | E48: =IFERROR(B48/D48+C48/D48,0)/2 -> 0.5
A49: Direct Costs | B49: =B29 -> 140204.25 | C49: =C29 -> 315369 | D49: =D29 -> 455573.25 | E49: =IFERROR(B49/D49+C49/D49,0)/2 -> 0.5
A50: Gross Profit | B50: =B48-B49 -> 556458.25 | C50: =C48-C49 -> 2079987 | D50: =D48-D49 -> 2636445.2 | E50: =IFERROR(B50/D50+C50/D50,0)/2 -> 0.5
A51: Gross Margin % | B51: =IFERROR(B50/B48,0) -> 0.79874868 | C51: =IFERROR(C50/C48,0) -> 0.86834149 | D51: =IFERROR(D50/D48,0) -> 0.85266154 | E51: —
A52: Indirect Costs | B52: =B42 -> 94800 | C52: =C42 -> 431050 | D52: =D42 -> 525850 | E52: =IFERROR(B52/D52+C52/D52,0)/2 -> 0.5
A53: NET CONTRIBUTION | B53: =B50-B52 -> 461658.25 | C53: =C50-C52 -> 1648937 | D53: =D50-D52 -> 2110595.2 | E53: =IFERROR(B53/D53+C53/D53,0)/2 -> 0.5
A56: VOLUME SNAPSHOT
A57: Active physical customers | E57: ='11. Founders — Inputs'!B5 -> 2000
A58: Active AGP customers (organic + sign-up) | E58: ='16. AGP — Math'!D16 -> 3785
A59: Founder Savings Patrons (across 5 gates) | E59: ='13. Founders — Aggregate'!C11 -> 712
A60: AGP Sign-ups generated (6-mo campaign) | E60: ='18. AGP Sign-up — Math'!C12 -> 2500
A61: AGP customers from Sign-up campaign | E61: ='18. AGP Sign-up — Math'!C18 -> 1625

Sheet 2. Summary
A1: AURUM — INVESTOR SUMMARY | I1: ↑ P&L | P1: ↑ P&L
A2: One-page snapshot of the entire model. All numbers auto-pull from source tabs. Designed for quick reads with investors.
A4: HEADLINE NUMBERS
A5: Y1 REVENUE | C5: Y5 REVENUE | E5: Y1 EBITDA | G5: Y5 EBITDA
A6: ='1. P&L Summary'!D18 -> 3092018.5 | C6: ='3. 5-Year Forecast'!F19 -> 21173519 | E6: ='1. P&L Summary'!D53 -> 2110595.2 | G6: ='3. 5-Year Forecast'!F29 -> 15761990
A7: Y5 GROSS MARGIN | C7: CUMULATIVE 5Y EBITDA | E7: CASH NEEDED TO LAUNCH | G7: POST-MONEY VALUATION
A8: ='3. 5-Year Forecast'!F23 -> 0.85235843 | C8: ='3. 5-Year Forecast'!F31 -> 44429259 | E8: ='7. Start-up Requirements'!E69 -> 1462038 | G8: ='8. Equity Structure'!B9 -> 20365510
A10: VOLUME & GMV (Y1 base case)
A11: Total active customers (Y1) | D11: ='11. Founders — Inputs'!B5+'16. AGP — Math'!D16 -> 5785 | F11: Physical + AGP
A12: Founder Savings Patrons | D12: ='13. Founders — Aggregate'!C11 -> 712 | F12: Across 5 gates
A13: AGP active customers | D13: ='16. AGP — Math'!D16 -> 3785 | F13: Organic + sign-up
A14: Total annual GMV (Y1) | D14: =SUMPRODUCT('11. Founders — Inputs'!C14:C18,'13. Founders — Aggregate'!C5:C9)+'16. AGP — Math'!F27+'18. AGP Sign-up — Math'!G12+('17. AGP Sign-up — Inputs'!B16*(1-'17. AGP Sign-up — Inputs'!B17))*'4. Pricing Levers'!B27*'4. Pricing Levers'!B28 -> 31555270 | F14: All channels
A15: Take rate (Revenue / GMV) | D15: ='1. P&L Summary'!D18/(SUMPRODUCT('11. Founders — Inputs'!C14:C18,'13. Founders — Aggregate'!C5:C9)+'16. AGP — Math'!F27+'18. AGP Sign-up — Math'!G12+('17. AGP Sign-up — Inputs'!B16*(1-'17. AGP Sign-up — Inputs'!B17))*'4. Pricing Levers'!B27*'4. Pricing Levers'!B28) -> 0.097987387 | F15: Computed
A17: REVENUE BREAKDOWN (Y1)
A18: Premium — Founders Plan | D18: ='1. P&L Summary'!D7 -> 679250 | F18: =C18/'1. P&L Summary'!D18 -> 0
A19: Premium — AGP Plan | D19: ='1. P&L Summary'!D8 -> 2310188.1 | F19: =C19/'1. P&L Summary'!D18 -> 0
A20: Premium — Basic | D20: ='1. P&L Summary'!D9 -> 8312.5 | F20: =C20/'1. P&L Summary'!D18 -> 0
A21: Storage fees | D21: ='1. P&L Summary'!D12 -> 58838.8 | F21: =C21/'1. P&L Summary'!D18 -> 0
A22: Sell-back spread | D22: ='1. P&L Summary'!D13 -> 1500 | F22: =C22/'1. P&L Summary'!D18 -> 0
A23: AGP+ subscription | D23: ='1. P&L Summary'!D14 -> 31794 | F23: =C23/'1. P&L Summary'!D18 -> 0
A24: Insurance add-on | D24: ='1. P&L Summary'!D15 -> 2135.0016 | F24: =C24/'1. P&L Summary'!D18 -> 0
A25: TOTAL Y1 REVENUE | D25: ='1. P&L Summary'!D18 -> 3092018.5 | F25: 1
A27: 5-YEAR P&L TRAJECTORY
A28: Line Item | B28: Y1 | C28: Y2 | D28: Y3 | E28: Y4 | F28: Y5 | G28: 5Y Total | H28: CAGR
A29: Total Revenue | B29: ='3. 5-Year Forecast'!B19 -> 3092018.5 | C29: ='3. 5-Year Forecast'!C19 -> 7381714.9 | D29: ='3. 5-Year Forecast'!D19 -> 11072572 | E29: ='3. 5-Year Forecast'!E19 -> 16399860 | F29: ='3. 5-Year Forecast'!F19 -> 21173519 | G29: ='3. 5-Year Forecast'!G19 -> 59119684 | H29: ='3. 5-Year Forecast'!H19 -> 0.61766183
A30: Direct Costs | B30: ='3. 5-Year Forecast'!B21 -> 455573.25 | C30: ='3. 5-Year Forecast'!C21 -> 973787.82 | D30: ='3. 5-Year Forecast'!D21 -> 1533715.8 | E30: ='3. 5-Year Forecast'!E21 -> 2335082.3 | F30: ='3. 5-Year Forecast'!F21 -> 3126091.5 | G30: ='3. 5-Year Forecast'!G21 -> 8424250.7 | H30: ='3. 5-Year Forecast'!H21 -> 0.61849315
A31: Gross Profit | B31: ='3. 5-Year Forecast'!B22 -> 2636445.2 | C31: ='3. 5-Year Forecast'!C22 -> 6407927.1 | D31: ='3. 5-Year Forecast'!D22 -> 9538856.5 | E31: ='3. 5-Year Forecast'!E22 -> 14064777 | F31: ='3. 5-Year Forecast'!F22 -> 18047427 | G31: ='3. 5-Year Forecast'!G22 -> 50695433 | H31: ='3. 5-Year Forecast'!H22 -> 0
A32: Gross Margin % | B32: ='3. 5-Year Forecast'!B23 -> 0.85266154 | C32: ='3. 5-Year Forecast'!C23 -> 0.86808108 | D32: ='3. 5-Year Forecast'!D23 -> 0.86148514 | E32: ='3. 5-Year Forecast'!E23 -> 0.85761571 | F32: ='3. 5-Year Forecast'!F23 -> 0.85235843 | G32: ='3. 5-Year Forecast'!G23 -> 0.85844038 | H32: ='3. 5-Year Forecast'!H23 -> 0
A33: Total Indirect | B33: ='3. 5-Year Forecast'!B27 -> 525850 | C33: ='3. 5-Year Forecast'!C27 -> 769815 | D33: ='3. 5-Year Forecast'!D27 -> 1101634.5 | E33: ='3. 5-Year Forecast'!E27 -> 1583437.4 | F33: ='3. 5-Year Forecast'!F27 -> 2285437.3 | G33: ='3. 5-Year Forecast'!G27 -> 6266174.2 | H33: ='3. 5-Year Forecast'!H27 -> 0
A34: EBITDA | B34: ='3. 5-Year Forecast'!B29 -> 2110595.2 | C34: ='3. 5-Year Forecast'!C29 -> 5638112.1 | D34: ='3. 5-Year Forecast'!D29 -> 8437222 | E34: ='3. 5-Year Forecast'!E29 -> 12481340 | F34: ='3. 5-Year Forecast'!F29 -> 15761990 | G34: ='3. 5-Year Forecast'!G29 -> 44429259 | H34: ='3. 5-Year Forecast'!H29 -> 0
A35: EBITDA Margin | B35: ='3. 5-Year Forecast'!B30 -> 0.68259463 | C35: ='3. 5-Year Forecast'!C30 -> 0.76379434 | D35: ='3. 5-Year Forecast'!D30 -> 0.76199295 | E35: ='3. 5-Year Forecast'!E30 -> 0.76106383 | F35: ='3. 5-Year Forecast'!F30 -> 0.74441996 | G35: ='3. 5-Year Forecast'!G30 -> 0.74277314 | H35: ='3. 5-Year Forecast'!H30 -> 0
A37: VC METRICS — Y5 SNAPSHOT
A38: CAC (Customer Acquisition Cost) | D38: ='3. 5-Year Forecast'!F46 -> 200.54967 | F38: <$200 healthy
A39: LTV (Customer Lifetime Value) | D39: ='3. 5-Year Forecast'!F47 -> 1418.0425 | F39: >$1K healthy
A40: LTV / CAC ratio | D40: ='3. 5-Year Forecast'!F48 -> 7.0707795 | F40: >3x healthy
A41: CAC Payback (months) | D41: ='3. 5-Year Forecast'!F49 -> 5.0913764 | F41: <24 mo healthy
A42: Rule of 40 | D42: ='3. 5-Year Forecast'!F52 -> 1.04442 | F42: >40% healthy
A44: EQUITY & RAISE STRUCTURE
A45: Pre-money valuation | D45: ='8. Equity Structure'!B8 -> 20000000
A46: Post-money valuation | D46: ='8. Equity Structure'!B9 -> 20365510
A47: Equity round size | D47: ='8. Equity Structure'!B6 -> 0.25
A48: Cash raised total | D48: ='7. Start-up Requirements'!B77 -> 1462039
A49: · Founders contribution | D49: ='7. Start-up Requirements'!B74 -> 219306
A50: · SAFE / convertible note | D50: ='7. Start-up Requirements'!B75 -> 292408
A51: · Seed equity round | D51: ='7. Start-up Requirements'!B76 -> 950325
A52: Post-seed equity — Thomas K. Jung | D52: ='8. Equity Structure'!E28 -> 0.28365046
A53: Post-seed equity — Jae Chung | D53: ='8. Equity Structure'!E29 -> 0.28365046
A54: Post-seed equity — Brian Lee | D54: ='8. Equity Structure'!E30 -> 0.28365046
A55: Post-seed equity — ESOP | D55: ='8. Equity Structure'!E31 -> 0.094550152
A56: Post-seed equity — SAFE holders | D56: ='8. Equity Structure'!E32 -> 0.036551
A57: Post-seed equity — New investors | D57: ='8. Equity Structure'!E33 -> 0.017947476
A59: BALANCE SHEET & CASH FLOW (Y5)
A60: Y5 cash on balance sheet | D60: ='10. Cash Flow'!G31 -> 47993195
A61: Y5 total assets | D61: ='9. Balance Sheet'!G12 -> 1.5753845e+08
A62: Y5 customer deposits (custodial) | D62: ='9. Balance Sheet'!G16 -> 108609480
A63: Y5 free cash flow | D63: ='10. Cash Flow'!G35 -> 15642125
A64: 5Y cumulative free cash flow | D64: =SUM('10. Cash Flow'!C35:G35) -> 43859481
A67: STRATEGIC RECOMMENDATIONS — TOP PRIORITIES
A68: I | B68: Lead with Founders Plan — relationships not funnels | H68: CRITICAL
A69: II | B69: Run AGP Sign-up campaign as launch accelerant (months 6-12) | H69: HIGH
A70: III | B70: Hold storage fees at 0.5% AUC — AUC growth > storage revenue | H70: HIGH
A71: IV | B71: Negotiate wholesale spread aggressively — 0.25% = pure margin at scale | H71: HIGH
A72: V | B72: Do not underspend on PSPM/PIPA — moat depends on it | H72: CRITICAL
A73: VI | B73: Singapore vault is the differentiator — communicate relentlessly | H73: HIGH
A74: VII | B74: Reinvest first 18 months EBITDA — no distributions until Y4+ | H74: STANDARD
A75: VIII | B75: Premium drift annually 5% — Korean retail at +20-30% sets the reference | H75: STANDARD
A78: ONE-LINE BUSINESS CASE
A79: Korean MZ HNW investors pay a 20-30% domestic premium for trapped physical gold. Aurum offers them international spot + Singapore FTZ vault custody — turning the savings into a recurring AGP relationship that compounds. Capital-efficient by Year 2, gross-margin attractive throughout, and the Singapore + LBMA chain is a moat domestic Korean entrants cannot replicate inside 18 months.
A81: — Aurum Pte Ltd | Founders: Thomas K. Jung, Jae Chung, Brian Lee | All projections directional; subject to market, regulatory, and execution risk.

Sheet 3. 5-Year Forecast
A1: AURUM — 5-YEAR FORECAST | I1: ↑ P&L | P1: ↑ P&L
A2: P&L 5-year base + VC metrics + charts. Y1 pulls from Master P&L. Growth via input multipliers.
A4: GROWTH ASSUMPTIONS
A5: Lever | B5: Y2 | C5: Y3 | D5: Y4 | E5: Y5 | F5: Notes
A6: Customer count growth (Physical) | B6: 2 | C6: 1.5 | D6: 1.4 | E6: 1.25 | F6: Year-over-year multiplier
A7: AGP customer growth | B7: 2.5 | C7: 1.5 | D7: 1.5 | E7: 1.3 | F7: Faster — recurring stickiness
A8: Premium drift (price increase) | B8: 1 | C8: 1 | D8: 1 | E8: 1 | F8: Modest annual increase
A9: Direct cost efficiency multiplier | B9: 0.95 | C9: 1.05 | D9: 1.05 | E9: 1.05 | F9: <1 = cost decreases per unit
A10: Indirect cost growth | B10: 1.4 | C10: 1.3 | D10: 1.3 | E10: 1.3 | F10: OpEx growth rate
A11: Marketing-Promotion intensity | B11: 1.5 | C11: 1.5 | D11: 1.5 | E11: 1.5 | F11: Drops after launch push
A14: 5-YEAR P&L (driven by Master P&L Y1 + growth assumptions)
A15: Line Item | B15: Y1 | C15: Y2 | D15: Y3 | E15: Y4 | F15: Y5 | G15: 5Y Total | H15: CAGR
A16: REVENUE
A17: Physical revenue | B17: ='1. P&L Summary'!B18 -> 696662.5 | C17: =B17*B6*B8 -> 1393325 | D17: =C17*C6*C8 -> 2089987.5 | E17: =D17*D6*D8 -> 2925982.5 | F17: =E17*E6*E8 -> 3657478.1 | G17: =SUM(B17:F17) -> 10763436 | H17: =IFERROR((F17/B17)^(1/4)-1,0) -> 0.51370005
A18: AGP revenue | B18: ='1. P&L Summary'!C18 -> 2395356 | C18: =B18*B7*B8 -> 5988389.9 | D18: =C18*C7*C8 -> 8982584.8 | E18: =D18*D7*D8 -> 13473877 | F18: =E18*E7*E8 -> 17516040 | G18: =SUM(B18:F18) -> 48356248 | H18: =IFERROR((F18/B18)^(1/4)-1,0) -> 0.64443408
A19: Total Revenue | B19: =B17+B18 -> 3092018.5 | C19: =C17+C18 -> 7381714.9 | D19: =D17+D18 -> 11072572 | E19: =E17+E18 -> 16399860 | F19: =F17+F18 -> 21173519 | G19: =SUM(B19:F19) -> 59119684 | H19: =IFERROR((F19/B19)^(1/4)-1,0) -> 0.61766183
A21: Direct Costs | B21: ='1. P&L Summary'!D29 -> 455573.25 | C21: =B21*(B6+B7)/2*B9 -> 973787.82 | D21: =C21*(C6+C7)/2*C9 -> 1533715.8 | E21: =D21*(D6+D7)/2*D9 -> 2335082.3 | F21: =E21*(E6+E7)/2*E9 -> 3126091.5 | G21: =SUM(B21:F21) -> 8424250.7 | H21: =IFERROR((F21/B21)^(1/4)-1,0) -> 0.61849315
A22: Gross Profit | B22: =B19-B21 -> 2636445.2 | C22: =C19-C21 -> 6407927.1 | D22: =D19-D21 -> 9538856.5 | E22: =E19-E21 -> 14064777 | F22: =F19-F21 -> 18047427 | G22: =SUM(B22:F22) -> 50695433
A23: Gross Margin % | B23: =IFERROR(B22/B19,0) -> 0.85266154 | C23: =IFERROR(C22/C19,0) -> 0.86808108 | D23: =IFERROR(D22/D19,0) -> 0.86148514 | E23: =IFERROR(E22/E19,0) -> 0.85761571 | F23: =IFERROR(F22/F19,0) -> 0.85235843 | G23: =AVERAGE(B23:F23) -> 0.85844038
A25: Marketing — Promotion | B25: ='1. P&L Summary'!D36 -> 336250 | C25: =B25*B11 -> 504375 | D25: =C25*C11 -> 756562.5 | E25: =D25*D11 -> 1134843.8 | F25: =E25*E11 -> 1702265.6 | G25: =SUM(B25:F25) -> 4434296.9 | H25: =IFERROR((F25/B25)^(1/4)-1,0) -> 0.5
A26: Other Indirect (Brand+Compliance+Tech+People) | B26: ='1. P&L Summary'!D42-'1. P&L Summary'!D36 -> 189600 | C26: =B26*B10 -> 265440 | D26: =C26*C10 -> 345072 | E26: =D26*D10 -> 448593.6 | F26: =E26*E10 -> 583171.68 | G26: =SUM(B26:F26) -> 1831877.3 | H26: =IFERROR((F26/B26)^(1/4)-1,0) -> 0.32430959
A27: Total Indirect | B27: =B25+B26 -> 525850 | C27: =C25+C26 -> 769815 | D27: =D25+D26 -> 1101634.5 | E27: =E25+E26 -> 1583437.4 | F27: =F25+F26 -> 2285437.3 | G27: =G25+G26 -> 6266174.2
A29: EBITDA (Net Contribution) | B29: =B22-B27 -> 2110595.2 | C29: =C22-C27 -> 5638112.1 | D29: =D22-D27 -> 8437222 | E29: =E22-E27 -> 12481340 | F29: =F22-F27 -> 15761990 | G29: =SUM(B29:F29) -> 44429259
A30: EBITDA Margin % | B30: =IFERROR(B29/B19,0) -> 0.68259463 | C30: =IFERROR(C29/C19,0) -> 0.76379434 | D30: =IFERROR(D29/D19,0) -> 0.76199295 | E30: =IFERROR(E29/E19,0) -> 0.76106383 | F30: =IFERROR(F29/F19,0) -> 0.74441996 | G30: =AVERAGE(B30:F30) -> 0.74277314
A31: Cumulative EBITDA | B31: =B29 -> 2110595.2 | C31: =B31+C29 -> 7748707.3 | D31: =C31+D29 -> 16185929 | E31: =D31+E29 -> 28667269 | F31: =E31+F29 -> 44429259
A34: CUSTOMER METRICS
A35: Metric | B35: Y1 | C35: Y2 | D35: Y3 | E35: Y4 | F35: Y5 | G35: 5Y Total/Avg | H35: CAGR
A36: Active Physical customers | B36: ='11. Founders — Inputs'!B5 -> 2000 | C36: =ROUND(B36*B6,0) -> 4000 | D36: =ROUND(C36*C6,0) -> 6000 | E36: =ROUND(D36*D6,0) -> 8400 | F36: =ROUND(E36*E6,0) -> 10500 | G36: =F36 -> 10500 | H36: =IFERROR((F36/B36)^(1/4)-1,0) -> 0.51370005
A37: Active AGP customers | B37: ='16. AGP — Math'!D16 -> 3785 | C37: =ROUND(B37*B7,0) -> 9463 | D37: =ROUND(C37*C7,0) -> 14195 | E37: =ROUND(D37*D7,0) -> 21293 | F37: =ROUND(E37*E7,0) -> 27681 | G37: =F37 -> 27681 | H37: =IFERROR((F37/B37)^(1/4)-1,0) -> 0.64448143
A38: Total active customers | B38: =B36+B37 -> 5785 | C38: =C36+C37 -> 13463 | D38: =D36+D37 -> 20195 | E38: =E36+E37 -> 29693 | F38: =F36+F37 -> 38181 | G38: =F38 -> 38181
A40: ARR (Annual Recurring Revenue) | B40: =B18+'1. P&L Summary'!D12+'1. P&L Summary'!D14 -> 2485988.8 | C40: =B40*B7*B8 -> 6214971.9 | D40: =C40*C7*C8 -> 9322457.8 | E40: =D40*D7*D8 -> 13983687 | F40: =E40*E7*E8 -> 18178793 | G40: =SUM(B40:F40) -> 50185898 | H40: =IFERROR((F40/B40)^(1/4)-1,0) -> 0.64443408
A41: ARR growth % | B41: — | C41: =(C40-B40)/B40 -> 1.5 | D41: =(D40-C40)/C40 -> 0.5 | E41: =(E40-D40)/D40 -> 0.5 | F41: =(F40-E40)/E40 -> 0.3
A44: VC METRICS
A45: Metric | B45: Y1 | C45: Y2 | D45: Y3 | E45: Y4 | F45: Y5 | G45: Definition | H45: Healthy?
A46: CAC (Customer Acquisition Cost) | B46: =B25/B38 -> 58.12446 | C46: =C25/(C38-B38) -> 65.690935 | D46: =D25/(D38-C38) -> 112.38302 | E46: =E25/(E38-D38) -> 119.48239 | F46: =F25/(F38-E38) -> 200.54967 | G46: Marketing-Promotion / New customers | H46: <$200
A47: LTV (Customer Lifetime Value) | B47: =B22/B38*3 -> 1367.2145 | C47: =C22/C38*3 -> 1427.8973 | D47: =D22/D38*3 -> 1417.0126 | E47: =E22/E38*3 -> 1421.0195 | F47: =F22/F38*3 -> 1418.0425 | G47: Gross profit per customer × 3 yr avg life | H47: >$1K
A48: LTV / CAC ratio | B48: =IFERROR(B47/B46,0) -> 23.522188 | C48: =IFERROR(C47/C46,0) -> 21.736596 | D48: =IFERROR(D47/D46,0) -> 12.608778 | E48: =IFERROR(E47/E46,0) -> 11.893129 | F48: =IFERROR(F47/F46,0) -> 7.0707795 | G48: Higher = more efficient growth | H48: >3x
A49: CAC Payback (months) | B49: =IFERROR(B46*12/(B22/B38),0) -> 1.5304699 | C49: =IFERROR(C46*12/(C22/C38),0) -> 1.6561931 | D49: =IFERROR(D46*12/(D22/D38),0) -> 2.8551537 | E49: =IFERROR(E46*12/(E22/E38),0) -> 3.0269578 | F49: =IFERROR(F46*12/(F22/F38),0) -> 5.0913764 | G49: Months to recover CAC from gross profit | H49: <24 mo
A50: NRR (Net Revenue Retention) | B50: ='15. AGP — Inputs'!B23 -> 0.73799835 | C50: ='15. AGP — Inputs'!B23*C8 -> 0.73799835 | D50: ='15. AGP — Inputs'!B23*D8 -> 0.73799835 | E50: ='15. AGP — Inputs'!B23*E8 -> 0.73799835 | F50: ='15. AGP — Inputs'!B23*E8 -> 0.73799835 | G50: Existing customer revenue retention | H50: >100%
A51: GRR (Gross Revenue Retention) | B51: ='15. AGP — Inputs'!B23 -> 0.73799835 | C51: ='15. AGP — Inputs'!B23 -> 0.73799835 | D51: ='15. AGP — Inputs'!B23 -> 0.73799835 | E51: ='15. AGP — Inputs'!B23 -> 0.73799835 | F51: ='15. AGP — Inputs'!B23 -> 0.73799835 | G51: Floor: pure retention without expansion | H51: >85%
A52: Rule of 40 (ARR growth + EBITDA margin) | B52: — | C52: =C41+C30 -> 2.2637943 | D52: =D41+D30 -> 1.2619929 | E52: =E41+E30 -> 1.2610638 | F52: =F41+F30 -> 1.04442 | G52: ARR growth + EBITDA margin | H52: >40%
A53: Magic Number | B53: — | C53: =IFERROR((C19-B19)*4/B25,0) -> 51.029846 | D53: =IFERROR((D19-C19)*4/C25,0) -> 29.270741 | E53: =IFERROR((E19-D19)*4/D25,0) -> 28.165749 | F53: =IFERROR((F19-E19)*4/E25,0) -> 16.825783 | G53: (ΔRevenue×4)/Prior Marketing — sales efficiency | H53: >0.75x
A54: Burn Multiple | B54: =IFERROR(MAX(0,-B29)/B19,0) -> 0 | C54: =IFERROR(MAX(0,-C29)/(C19-B19),0) -> 0 | D54: =IFERROR(MAX(0,-D29)/(D19-C19),0) -> 0 | E54: =IFERROR(MAX(0,-E29)/(E19-D19),0) -> 0 | F54: =IFERROR(MAX(0,-F29)/(F19-E19),0) -> 0 | G54: Net burn / Net new ARR — capital efficiency | H54: <1.5x

Sheet 4. Pricing Levers
A1: AURUM · PRICING LEVERS | I1: ↑ P&L | P1: ↑ P&L
A2: Premium structure that drives all downstream economics. All values in USD.
A4: AURUM PREMIUM CHARGE — THE PRIMARY LEVER
A5: Charged on top of international spot price. Editable. Drives all revenue lines.
A7: Aurum GOLD premium (% above spot) | B7: 0.08 | C7: Modify to test scenarios — typical 1.5%-5.0% for HNW physical bullion
A8: Aurum SILVER premium (% above spot) | B8: 0.13 | C8: Silver typically carries higher premium than gold (3%-8% range)
A9: % of customer GMV in gold | B9: 0.7 | C9: Korean MZ + HNW skew gold-heavy
A10: % of customer GMV in silver | B10: =1-B9 -> 0.3 | C10: (computed)
A12: BLENDED PREMIUM (gold-weighted + silver-weighted) | B12: =B7*B9+B8*B10 -> 0.095
A14: OTHER FEE LEVERS
A15: Allocated storage fee % / yr (charged to customer) | B15: 0.005 | C15: Aurum tiered
A16: AGP storage fee % / yr (charged) | B16: 0.005 | C16: Lower than allocated
A17: Malca-Amit storage pass-through % / yr | B17: 0.0025 | C17: What we pay vault
A18: Sell-back spread % (below spot) | B18: 0.005 | C18: Customer sells back
A19: Subscription price (AGP+) USD/month | B19: 7 | C19: Robinhood Gold-style
A20: Subscription tier adoption % of AGP | B20: 0.1 | C20: AGP+ opt-in rate
A21: Insurance add-on adoption % | B21: 0.08 | C21: Insurance opt-in
A22: Insurance add-on fee % on AUC | B22: 0.002 | C22: Fee charged
A23: Wholesale supplier spread % over spot (COGS) | B23: 0.01 | C23: LBMA refiner cost
A24: KYC/AML cost per new customer (USD) | B24: 15 | C24: Onboarding cost
A26: BASIC REVENUE LEVERS (one-off purchasers from sign-up funnel)
A27: % of non-converting signups who make a basic one-off purchase | B27: 0.2 | C27: Of signups that did NOT activate AGP
A28: Avg basic one-off purchase size (USD) | B28: 500 | C28: Single transaction average
A30: FIXED MONTHLY COSTS (USD)
A31: Compliance (PSPM, PIPA, audit) — monthly | B31: 2800 | C31: GC memo
A32: Tech platform — monthly | B32: 1500 | C32: Hosting, KYC vendor
A33: Personnel — monthly | B33: 6500 | C33: Founder + 1 part-time
A34: Marketing — Brand (always-on, monthly) | B34: 5000 | C34: Brand-building, organic
A36: SPOT PRICES (drives waterfalls)
A37: Global GOLD spot (USD/oz) | B37: 4842 | C37: GoldAPI live or manual
A38: Global SILVER spot (USD/oz) | B38: 79 | C38: Silver spot
A39: Korean GOLD retail (USD/oz, incl 10% VAT) | B39: =B37*1.2 -> 5810.4 | C39: kumsise/koreagoldx scrape
A40: Korean SILVER retail (USD/oz, incl VAT) | B40: =B38*1.3 -> 102.7 | C40: KR silver retail
A41: KRW/USD FX rate | B41: 1472 | C41: Live from open.er-api.com
A42: Korea VAT rate | B42: 0.1 | C42: Standard 10%
A45: VOLUME & GMV SNAPSHOT — pulled from all model tabs
A46: Executive snapshot — customer counts, GMV, revenue by category. All figures auto-pull from source tabs.
A48: 👥 CUSTOMER COUNTS (annual base case)
A49: Metric | B49: Value | C49: Source
A50: Active physical customers (M6 base) | B50: ='11. Founders — Inputs'!B5 -> 2000 | C50: Tab 5
A51: Founder Savings Patrons (across 5 gates) | B51: ='13. Founders — Aggregate'!C11 -> 712 | C51: Tab 7
A52: Active AGP customers (organic + sign-up) | B52: ='16. AGP — Math'!D16 -> 3785 | C52: Tab 10
A53: AGP customers from sign-up campaign | B53: ='18. AGP Sign-up — Math'!C18 -> 1625 | C53: Tab 12
A54: Total signups (6-mo campaign) | B54: ='18. AGP Sign-up — Math'!C12 -> 2500 | C54: Tab 12
A55: Total active customers (Y1) | B55: ='11. Founders — Inputs'!B5+'16. AGP — Math'!D16 -> 5785 | C55: Combined
A57: 💰 GMV (Gross Merchandise Value, annual)
A58: Metric | B58: Value | C58: Source
A59: Founders Plan GMV (5 gates × patrons) | B59: =SUMPRODUCT('11. Founders — Inputs'!C14:C18,'13. Founders — Aggregate'!C5:C9) -> 7150000 | C59: Tabs 5+7
A60: AGP Plan GMV (organic + sign-up campaign) | B60: ='16. AGP — Math'!F27+'18. AGP Sign-up — Math'!G12 -> 24317770 | C60: Tabs 10+12
A61: Basic one-off purchases GMV | B61: =('17. AGP Sign-up — Inputs'!B16*(1-'17. AGP Sign-up — Inputs'!B17))*B27*B28 -> 87500 | C61: Tab 11 × levers
A62: TOTAL ANNUAL GMV | B62: =SUMPRODUCT('11. Founders — Inputs'!C14:C18,'13. Founders — Aggregate'!C5:C9)+'16. AGP — Math'!F27+'18. AGP Sign-up — Math'!G12+('17. AGP Sign-up — Inputs'!B16*(1-'17. AGP Sign-up — Inputs'!B17))*B27*B28 -> 31555270 | C62: Sum
A64: 💵 REVENUE BY CATEGORY (annual)
A65: Category | B65: Revenue | C65: % of Total
A66: Premium — Founders Plan | B66: ='1. P&L Summary'!D7 -> 679250 | C66: =B66/'1. P&L Summary'!D18 -> 0.21967851
A67: Premium — AGP Plan | B67: ='1. P&L Summary'!D8 -> 2310188.1 | C67: =B67/'1. P&L Summary'!D18 -> 0.74714565
A68: Premium — Basic | B68: ='1. P&L Summary'!D9 -> 8312.5 | C68: =B68/'1. P&L Summary'!D18 -> 0.0026883733
A69: Storage fees | B69: ='1. P&L Summary'!D12 -> 58838.8 | C69: =B69/'1. P&L Summary'!D18 -> 0.019029253
A70: Sell-back spread | B70: ='1. P&L Summary'!D13 -> 1500 | C70: =B70/'1. P&L Summary'!D18 -> 0.00048512
A71: AGP+ subscription | B71: ='1. P&L Summary'!D14 -> 31794 | C71: =B71/'1. P&L Summary'!D18 -> 0.010282604
A72: Insurance add-on | B72: ='1. P&L Summary'!D15 -> 2135.0016 | C72: =B72/'1. P&L Summary'!D18 -> 0.00069048799
A73: TOTAL ANNUAL REVENUE | B73: ='1. P&L Summary'!D18 -> 3092018.5 | C73: 1
A75: 📊 TAKE RATE & CONTRIBUTION
A76: Metric | B76: Value | C76: Source
A77: Take rate (Revenue / GMV) | B77: =B78/B79 -> 0.097987387 | C77: Revenue ÷ GMV
A78: Total revenue | B78: ='1. P&L Summary'!D18 -> 3092018.5 | C78: Tab 1 D18
A79: Total GMV | B79: =SUMPRODUCT('11. Founders — Inputs'!C14:C18,'13. Founders — Aggregate'!C5:C9)+'16. AGP — Math'!F27+'18. AGP Sign-up — Math'!G12+('17. AGP Sign-up — Inputs'!B16*(1-'17. AGP Sign-up — Inputs'!B17))*B27*B28 -> 31555270 | C79: Sum
A80: Net contribution (EBITDA proxy) | B80: ='1. P&L Summary'!D53 -> 2110595.2 | C80: Tab 1 D53
A81: Contribution margin % | B81: ='1. P&L Summary'!D53/'1. P&L Summary'!D18 -> 0.68259463 | C81: Tab 1

Sheet 5. Gold Pricing Waterfall
A1: GOLD PRICING WATERFALL — KOREAN RETAIL vs AURUM | I1: ↑ P&L | P1: ↑ P&L
A2: Build-up of Aurum gold pricing vs Korean retail. Per oz and per transaction. All inputs link to Pricing Levers.
A4: TOGGLES & FX
A5: Display unit | B5: oz | C5: Type "oz" / "g" / "돈" — affects conversion factor
A6: Conversion factor (per unit) | B6: =IF(B5="g",1/31.1035,IF(B5="돈",3.75/31.1035,1)) -> 1 | C6: oz=1, g=0.0322, 돈(3.75g)=0.1206
A7: KRW/USD FX | B7: ='4. Pricing Levers'!B41 -> 1472 | C7: From Pricing Levers
A9: SPOT PRICES (linked from Pricing Levers)
A10: Source | B10: USD/oz | C10: KRW/oz | D10: USD/unit | E10: KRW/unit | F10: Note
A11: Global gold spot | B11: ='4. Pricing Levers'!B37 -> 4842 | C11: =B11*B7 -> 7127424 | D11: =B11*B6 -> 4842 | E11: =C11*B6 -> 7127424 | F11: GoldAPI feed
A12: Korean gold retail (incl 10% VAT) | B12: ='4. Pricing Levers'!B39 -> 5810.4 | C12: =B12*B7 -> 8552908.8 | D12: =B12*B6 -> 5810.4 | E12: =C12*B6 -> 8552908.8 | F12: kumsise/koreagoldx 1g × 31.1035
A14: Korean retail premium over global spot | B14: =B12-B11 -> 968.4 | C14: =B14*B7 -> 1425484.8 | D14: =(B12-B11)/B11 -> 0.2 | F14: AKA "kimchi premium" — Aurum captures portion
A16: AURUM GOLD PREMIUM — WHAT THE PREMIUM COVERS
A17: Cost Component | B17: Est. % of spot | C17: USD/oz | D17: KRW/oz | E17: Description
A18: Wholesale spread (refiner COGS) | B18: ='4. Pricing Levers'!B23 -> 0.01 | C18: =B18*$B$11 -> 48.42 | D18: =C18*$B$7 -> 71274.24 | E18: What we pay LBMA refiner above spot
A19: Vault storage pass-through | B19: ='4. Pricing Levers'!B17 -> 0.0025 | C19: =B19*$B$11 -> 12.105 | D19: =C19*$B$7 -> 17818.56 | E19: Malca-Amit annual storage cost
A20: Insurance & logistics | B20: 0.002 | C20: =B20*$B$11 -> 9.684 | D20: =C20*$B$7 -> 14254.848 | E20: Lloyds coverage + CJ Logistics
A21: KYC / compliance overhead | B21: 0.001 | C21: =B21*$B$11 -> 4.842 | D21: =C21*$B$7 -> 7127.424 | E21: PASS verification + AML
A22: Platform operating margin | B22: ='4. Pricing Levers'!B7-B18-B19-B20-B21 -> 0.0645 | C22: =B22*$B$11 -> 312.309 | D22: =C22*$B$7 -> 459718.85 | E22: Remainder = Aurum net margin
A23: Aurum Gold premium (from Pricing Levers) | B23: ='4. Pricing Levers'!B7 -> 0.08 | C23: =B23*$B$11 -> 387.36 | D23: =C23*$B$7 -> 570193.92 | E23: Pulled from Pricing Levers — single source of truth
A24: Check: component sum vs premium | B24: =SUM(B18:B22)-B23 -> 0 | E24: Should be 0 — if not, platform margin auto-adjusts
A26: GOLD PRICING WATERFALL — SPOT TO CUSTOMER PRICE
A27: Step | B27: USD/oz | C27: KRW/oz | D27: USD/unit | E27: KRW/unit | F27: Note
A28: Global gold spot | B28: =B11 -> 4842 | C28: =B28*$B$7 -> 7127424 | D28: =B28*$B$6 -> 4842 | E28: =C28*$B$6 -> 7127424 | F28: Live spot price
A29: + Wholesale spread (LBMA refiner cost) | B29: =B11*'4. Pricing Levers'!B23 -> 48.42 | C29: =B29*$B$7 -> 71274.24 | D29: =B29*$B$6 -> 48.42 | E29: =C29*$B$6 -> 71274.24 | F29: COGS — what we pay the refiner
A30: Aurum cost basis | B30: =B28+B29 -> 4890.42 | C30: =B30*$B$7 -> 7198698.2 | D30: =B30*$B$6 -> 4890.42 | E30: =C30*$B$6 -> 7198698.2 | F30: Our all-in cost per oz
A31: + Aurum gold premium | B31: =B11*'4. Pricing Levers'!B7 -> 387.36 | C31: =B31*$B$7 -> 570193.92 | D31: =B31*$B$6 -> 387.36 | E31: =C31*$B$6 -> 570193.92 | F31: Premium from Pricing Levers (Gold)
A33: AURUM GOLD LIST PRICE | B33: =B30+B31 -> 5277.78 | C33: =B33*$B$7 -> 7768892.2 | D33: =B33*$B$6 -> 5277.78 | E33: =C33*$B$6 -> 7768892.2 | F33: What the customer pays per oz
A34: Korean gold retail (incl 10% VAT) | B34: =B12 -> 5810.4 | C34: =B34*$B$7 -> 8552908.8 | D34: =B34*$B$6 -> 5810.4 | E34: =C34*$B$6 -> 8552908.8 | F34: Customer reference price — what they pay in Korea
A35: Customer savings with Aurum | B35: =B34-B33 -> 532.62 | C35: =B35*$B$7 -> 784016.64 | D35: =B35*$B$6 -> 532.62 | E35: =C35*$B$6 -> 784016.64 | F35: How much less customer pays vs Korea
A36: Savings % | B36: =B35/B34 -> 0.091666667 | F36: vs Korean retail — key customer message
A39: CUSTOMER VALUE COMPARISON
A40: Metric | B40: USD/oz | C40: KRW/oz | D40: % vs Korean retail
A41: Aurum List Price | B41: =B33 -> 5277.78 | C41: =B41*$B$7 -> 7768892.2 | D41: =B41/B12 -> 0.90833333 | J41: Source | K41: USD/oz
A42: Korean retail (incl VAT) | B42: =B12 -> 5810.4 | C42: =B42*$B$7 -> 8552908.8 | D42: =1 -> 1 | J42: Aurum Gold | K42: =B33 -> 5277.78
A43: Customer savings vs Korea | B43: =B12-B33 -> 532.62 | C43: =B43*$B$7 -> 784016.64 | D43: =B43/B12 -> 0.091666667 | J43: Korean Retail | K43: =B12 -> 5810.4
A46: PER-TRANSACTION VIEW (sample sizes)
A47: Transaction Size | B47: oz at Aurum List | C47: Aurum Revenue | D47: Aurum COGS | E47: Gross Margin $ | F47: Gross Margin % | G47: Customer Savings vs Korea
A48: 500 | B48: =A48/B33 -> 0.094736802 | C48: =A48 -> 500 | D48: =B48*B30 -> 463.30275 | E48: =C48-D48 -> 36.697248 | F48: =E48/C48 -> 0.073394495 | G48: =B48*(B12-B33) -> 50.458716
A49: 1000 | B49: =A49/B33 -> 0.1894736 | C49: =A49 -> 1000 | D49: =B49*B30 -> 926.6055 | E49: =C49-D49 -> 73.394495 | F49: =E49/C49 -> 0.073394495 | G49: =B49*(B12-B33) -> 100.91743
A50: 5000 | B50: =A50/B33 -> 0.94736802 | C50: =A50 -> 5000 | D50: =B50*B30 -> 4633.0275 | E50: =C50-D50 -> 366.97248 | F50: =E50/C50 -> 0.073394495 | G50: =B50*(B12-B33) -> 504.58716
A51: 25000 | B51: =A51/B33 -> 4.7368401 | C51: =A51 -> 25000 | D51: =B51*B30 -> 23165.138 | E51: =C51-D51 -> 1834.8624 | F51: =E51/C51 -> 0.073394495 | G51: =B51*(B12-B33) -> 2522.9358
A52: 100000 | B52: =A52/B33 -> 18.94736 | C52: =A52 -> 100000 | D52: =B52*B30 -> 92660.55 | E52: =C52-D52 -> 7339.4495 | F52: =E52/C52 -> 0.073394495 | G52: =B52*(B12-B33) -> 10091.743
A55: SENSITIVITY — AURUM PREMIUM VS MARGIN PER TRANSACTION
A56: Aurum Premium % | B56: List Price USD/oz | C56: Margin/oz | D56: Margin % per txn | E56: On $5K txn ($) | F56: On $25K txn ($)
A57: 0.1 | B57: =B11*(1+A57) -> 5326.2 | C57: =B57-B30 -> 435.78 | D57: =C57/B57 -> 0.081818182 | E57: =5000*C57/B57 -> 409.09091 | F57: =25000*C57/B57 -> 2045.4545
A58: 0.11 | B58: =B11*(1+A58) -> 5374.62 | C58: =B58-B30 -> 484.2 | D58: =C58/B58 -> 0.09009009 | E58: =5000*C58/B58 -> 450.45045 | F58: =25000*C58/B58 -> 2252.2523
B59: =B11*(1+A59) -> 4842 | C59: =B59-B30 -> -48.42 | D59: =C59/B59 -> -0.01 | E59: =5000*C59/B59 -> -50 | F59: =25000*C59/B59 -> -250
A60: 0.08 | B60: =B11*(1+A60) -> 5229.36 | C60: =B60-B30 -> 338.94 | D60: =C60/B60 -> 0.064814815 | E60: =5000*C60/B60 -> 324.07407 | F60: =25000*C60/B60 -> 1620.3704
B61: =B11*(1+A61) -> 4842 | C61: =B61-B30 -> -48.42 | D61: =C61/B61 -> -0.01 | E61: =5000*C61/B61 -> -50 | F61: =25000*C61/B61 -> -250
A62: 0.15 | B62: =B11*(1+A62) -> 5568.3 | C62: =B62-B30 -> 677.88 | D62: =C62/B62 -> 0.12173913 | E62: =5000*C62/B62 -> 608.69565 | F62: =25000*C62/B62 -> 3043.4783
A63: 0.16 | B63: =B11*(1+A63) -> 5616.72 | C63: =B63-B30 -> 726.3 | D63: =C63/B63 -> 0.12931034 | E63: =5000*C63/B63 -> 646.55172 | F63: =25000*C63/B63 -> 3232.7586
A64: 0.17 | B64: =B11*(1+A64) -> 5665.14 | C64: =B64-B30 -> 774.72 | D64: =C64/B64 -> 0.13675214 | E64: =5000*C64/B64 -> 683.76068 | F64: =25000*C64/B64 -> 3418.8034

Sheet 6. Silver Pricing Waterfall
A1: SILVER PRICING WATERFALL — KOREAN RETAIL vs AURUM | I1: ↑ P&L | P1: ↑ P&L
A2: Build-up of Aurum silver pricing vs Korean retail. Same structure as gold tab.
A4: TOGGLES & FX
A5: Display unit | B5: oz | C5: Type "oz" / "g" / "돈"
A6: Conversion factor (per unit) | B6: =IF(B5="g",1/31.1035,IF(B5="돈",3.75/31.1035,1)) -> 1
A7: KRW/USD FX | B7: ='4. Pricing Levers'!B41 -> 1472
A9: SPOT PRICES
A10: Source | B10: USD/oz | C10: KRW/oz | D10: USD/unit | E10: KRW/unit | F10: Note
A11: Global silver spot | B11: ='4. Pricing Levers'!B38 -> 79 | C11: =B11*B7 -> 116288 | D11: =B11*B6 -> 79 | E11: =C11*B6 -> 116288 | F11: Live silver spot
A12: Korean silver retail (incl 10% VAT) | B12: ='4. Pricing Levers'!B40 -> 102.7 | C12: =B12*B7 -> 151174.4 | D12: =B12*B6 -> 102.7 | E12: =C12*B6 -> 151174.4 | F12: KR silver retail
A14: Korean retail premium over global spot | B14: =B12-B11 -> 23.7 | C14: =B14*B7 -> 34886.4 | D14: =(B12-B11)/B11 -> 0.3 | F14: Korean silver retail markup
A16: AURUM SILVER PREMIUM — WHAT THE PREMIUM COVERS
A17: Cost Component | B17: Est. % of spot | C17: USD/oz | D17: KRW/oz | E17: Description
A18: Wholesale spread (refiner COGS) | B18: ='4. Pricing Levers'!B23 -> 0.01 | C18: =B18*$B$11 -> 0.79 | D18: =C18*$B$7 -> 1162.88 | E18: What we pay LBMA refiner above spot
A19: Vault storage pass-through | B19: ='4. Pricing Levers'!B17 -> 0.0025 | C19: =B19*$B$11 -> 0.1975 | D19: =C19*$B$7 -> 290.72 | E19: Malca-Amit annual storage cost
A20: Insurance & logistics | B20: 0.002 | C20: =B20*$B$11 -> 0.158 | D20: =C20*$B$7 -> 232.576 | E20: Lloyds coverage + CJ Logistics
A21: KYC / compliance overhead | B21: 0.001 | C21: =B21*$B$11 -> 0.079 | D21: =C21*$B$7 -> 116.288 | E21: PASS verification + AML
A22: Platform operating margin | B22: ='4. Pricing Levers'!B8-B18-B19-B20-B21 -> 0.1145 | C22: =B22*$B$11 -> 9.0455 | D22: =C22*$B$7 -> 13314.976 | E22: Remainder = Aurum net margin
A23: Aurum Silver premium (from Pricing Levers) | B23: ='4. Pricing Levers'!B8 -> 0.13 | C23: =B23*$B$11 -> 10.27 | D23: =C23*$B$7 -> 15117.44 | E23: Pulled from Pricing Levers — single source of truth
A24: Check: component sum vs premium | B24: =SUM(B18:B22)-B23 -> 0 | E24: Should be 0 — if not, platform margin auto-adjusts
A26: SILVER PRICING WATERFALL — SPOT TO CUSTOMER PRICE
A27: Step | B27: USD/oz | C27: KRW/oz | D27: USD/unit | E27: KRW/unit | F27: Note
A28: Global silver spot | B28: =B11 -> 79 | C28: =B28*$B$7 -> 116288 | D28: =B28*$B$6 -> 79 | E28: =C28*$B$6 -> 116288 | F28: Live spot price
A29: + Wholesale spread (LBMA refiner cost) | B29: =B11*'4. Pricing Levers'!B23 -> 0.79 | C29: =B29*$B$7 -> 1162.88 | D29: =B29*$B$6 -> 0.79 | E29: =C29*$B$6 -> 1162.88 | F29: COGS — what we pay the refiner
A30: Aurum cost basis | B30: =B28+B29 -> 79.79 | C30: =B30*$B$7 -> 117450.88 | D30: =B30*$B$6 -> 79.79 | E30: =C30*$B$6 -> 117450.88 | F30: Our all-in cost per oz
A31: + Aurum silver premium | B31: =B11*'4. Pricing Levers'!B8 -> 10.27 | C31: =B31*$B$7 -> 15117.44 | D31: =B31*$B$6 -> 10.27 | E31: =C31*$B$6 -> 15117.44 | F31: Premium from Pricing Levers (Silver)
A33: AURUM SILVER LIST PRICE | B33: =B30+B31 -> 90.06 | C33: =B33*$B$7 -> 132568.32 | D33: =B33*$B$6 -> 90.06 | E33: =C33*$B$6 -> 132568.32 | F33: What the customer pays per oz
A34: Korean silver retail (incl 10% VAT) | B34: =B12 -> 102.7 | C34: =B34*$B$7 -> 151174.4 | D34: =B34*$B$6 -> 102.7 | E34: =C34*$B$6 -> 151174.4 | F34: Customer reference price — what they pay in Korea
A35: Customer savings with Aurum | B35: =B34-B33 -> 12.64 | C35: =B35*$B$7 -> 18606.08 | D35: =B35*$B$6 -> 12.64 | E35: =C35*$B$6 -> 18606.08 | F35: How much less customer pays vs Korea
A36: Savings % | B36: =B35/B34 -> 0.12307692 | F36: vs Korean retail — key customer message
A39: CUSTOMER VALUE COMPARISON
A40: Metric | B40: USD/oz | C40: KRW/oz | D40: % vs Korean retail
A41: Aurum List Price | B41: =B33 -> 90.06 | C41: =B41*$B$7 -> 132568.32 | D41: =B41/B12 -> 0.87692308 | J41: Source | K41: USD/oz
A42: Korean retail (incl VAT) | B42: =B12 -> 102.7 | C42: =B42*$B$7 -> 151174.4 | D42: =1 -> 1 | J42: Aurum Silver | K42: =B33 -> 90.06
A43: Customer savings vs Korea | B43: =B12-B33 -> 12.64 | C43: =B43*$B$7 -> 18606.08 | D43: =B43/B12 -> 0.12307692 | J43: Korean Retail | K43: =B12 -> 102.7
A46: PER-TRANSACTION VIEW (sample sizes)
A47: Transaction Size | B47: oz at Aurum List | C47: Aurum Revenue | D47: Aurum COGS | E47: Gross Margin $ | F47: Gross Margin % | G47: Customer Savings vs Korea
A48: 500 | B48: =A48/B33 -> 5.5518543 | C48: =A48 -> 500 | D48: =B48*B30 -> 442.98246 | E48: =C48-D48 -> 57.017544 | F48: =E48/C48 -> 0.11403509 | G48: =B48*(B12-B33) -> 70.175439
A49: 1000 | B49: =A49/B33 -> 11.103709 | C49: =A49 -> 1000 | D49: =B49*B30 -> 885.96491 | E49: =C49-D49 -> 114.03509 | F49: =E49/C49 -> 0.11403509 | G49: =B49*(B12-B33) -> 140.35088
A50: 5000 | B50: =A50/B33 -> 55.518543 | C50: =A50 -> 5000 | D50: =B50*B30 -> 4429.8246 | E50: =C50-D50 -> 570.17544 | F50: =E50/C50 -> 0.11403509 | G50: =B50*(B12-B33) -> 701.75439
A51: 25000 | B51: =A51/B33 -> 277.59272 | C51: =A51 -> 25000 | D51: =B51*B30 -> 22149.123 | E51: =C51-D51 -> 2850.8772 | F51: =E51/C51 -> 0.11403509 | G51: =B51*(B12-B33) -> 3508.7719
A52: 100000 | B52: =A52/B33 -> 1110.3709 | C52: =A52 -> 100000 | D52: =B52*B30 -> 88596.491 | E52: =C52-D52 -> 11403.509 | F52: =E52/C52 -> 0.11403509 | G52: =B52*(B12-B33) -> 14035.088
A55: SENSITIVITY — AURUM SILVER PREMIUM VS MARGIN
A56: Aurum Premium % | B56: List Price USD/oz | C56: Margin/oz | D56: Margin % per txn | E56: On $5K txn ($) | F56: On $25K txn ($)
A57: 0.12 | B57: =B11*(1+A57) -> 88.48 | C57: =B57-B30 -> 8.69 | D57: =C57/B57 -> 0.098214286 | E57: =5000*C57/B57 -> 491.07143 | F57: =25000*C57/B57 -> 2455.3571
A58: 0.13 | B58: =B11*(1+A58) -> 89.27 | C58: =B58-B30 -> 9.48 | D58: =C58/B58 -> 0.10619469 | E58: =5000*C58/B58 -> 530.97345 | F58: =25000*C58/B58 -> 2654.8673
B59: =B11*(1+A59) -> 79 | C59: =B59-B30 -> -0.79 | D59: =C59/B59 -> -0.01 | E59: =5000*C59/B59 -> -50 | F59: =25000*C59/B59 -> -250
A60: 0.15 | B60: =B11*(1+A60) -> 90.85 | C60: =B60-B30 -> 11.06 | D60: =C60/B60 -> 0.12173913 | E60: =5000*C60/B60 -> 608.69565 | F60: =25000*C60/B60 -> 3043.4783
B61: =B11*(1+A61) -> 79 | C61: =B61-B30 -> -0.79 | D61: =C61/B61 -> -0.01 | E61: =5000*C61/B61 -> -50 | F61: =25000*C61/B61 -> -250
A62: 0.17 | B62: =B11*(1+A62) -> 92.43 | C62: =B62-B30 -> 12.64 | D62: =C62/B62 -> 0.13675214 | E62: =5000*C62/B62 -> 683.76068 | F62: =25000*C62/B62 -> 3418.8034
A63: 0.18 | B63: =B11*(1+A63) -> 93.22 | C63: =B63-B30 -> 13.43 | D63: =C63/B63 -> 0.1440678 | E63: =5000*C63/B63 -> 720.33898 | F63: =25000*C63/B63 -> 3601.6949

Sheet 7. Start-up Requirements
A1: AURUM — START-UP REQUIREMENTS | I1: ↑ P&L | P1: ↑ P&L
A2: Cash needed to launch. Categorized by program. 6-month runway baseline. Marketing rows pull from campaign budgets dynamically.
A4: Item | B4: One-Time | C4: Monthly | D4: 6-Mo Run | E4: Total Need | F4: Notes
A5: A. LEGAL & ENTITY SET-UP
A6: Singapore Pte Ltd incorporation | B6: 2500 | C6: 0 | D6: =C6*6 -> 0 | E6: =B6+D6 -> 2500 | F6: ACRA registration, company secretary year 1
A7: Singapore corporate bank account | B7: 1500 | C7: 0 | D7: =C7*6 -> 0 | E7: =B7+D7 -> 1500 | F7: OCBC or DBS — multi-currency
A8: Legal counsel (incorp, ToS, T&C) | B8: 15000 | C8: 0 | D8: =C8*6 -> 0 | E8: =B8+D8 -> 15000 | F8: Singapore + Korea cross-border review
A9: Trademark registration (Aurum + 한글) | B9: 8000 | C9: 0 | D9: =C9*6 -> 0 | E9: =B9+D9 -> 8000 | F9: WIPO Madrid + KIPO Korea direct
A10: Accounting set-up (Xero + advisor) | B10: 3000 | C10: 800 | D10: =C10*6 -> 4800 | E10: =B10+D10 -> 7800 | F10: Singapore tax + bookkeeping
A11: Subtotal | B11: =SUM(B6:B10) -> 30000 | C11: =SUM(C6:C10) -> 800 | D11: =SUM(D6:D10) -> 4800 | E11: =SUM(E6:E10) -> 34800
A13: B. COMPLIANCE — PSPM (SG) + PIPA (KR)
A14: PSPM payment services license prep | B14: 30000 | C14: 2500 | D14: =C14*6 -> 15000 | E14: =B14+D14 -> 45000 | F14: MAS application — required for stored value
A15: PIPA Korean privacy compliance | B15: 15000 | C15: 1500 | D15: =C15*6 -> 9000 | E15: =B15+D15 -> 24000 | F15: Personal Information Protection Act
A16: AML/CFT framework documentation | B16: 8000 | C16: 500 | D16: =C16*6 -> 3000 | E16: =B16+D16 -> 11000 | F16: STR/CTR procedures, board policy
A17: External compliance advisor retainer | B17: 5000 | C17: 3500 | D17: =C17*6 -> 21000 | E17: =B17+D17 -> 26000 | F17: PSPM + KR cross-border advisory
A18: Audit & internal controls (Y1) | B18: 12000 | C18: 0 | D18: =C18*6 -> 0 | E18: =B18+D18 -> 12000 | F18: Big 4 lite — Y1 baseline
A19: Subtotal | B19: =SUM(B14:B18) -> 70000 | C19: =SUM(C14:C18) -> 8000 | D19: =SUM(D14:D18) -> 48000 | E19: =SUM(E14:E18) -> 118000
A21: C. VAULT, REFINER & KYC VENDOR ONBOARDING
A22: Malca-Amit Singapore FTZ vault deposit | B22: 25000 | C22: 1200 | D22: =C22*6 -> 7200 | E22: =B22+D22 -> 32200 | F22: Refundable deposit + monthly minimum
A23: LBMA refiner relationship (Argor / PAMP) | B23: 10000 | C23: 0 | D23: =C23*6 -> 0 | E23: =B23+D23 -> 10000 | F23: KYB + line of credit set-up
A24: Inventory float — gold (working stock) | B24: 200000 | C24: 0 | D24: =C24*6 -> 0 | E24: =B24+D24 -> 200000 | F24: ~50 oz gold @ vault, growth float
A25: Inventory float — silver (working stock) | B25: 25000 | C25: 0 | D25: =C25*6 -> 0 | E25: =B25+D25 -> 25000 | F25: ~300 oz silver @ vault
A26: KYC vendor (NICE/KCB) integration | B26: 10000 | C26: 2000 | D26: =C26*6 -> 12000 | E26: =B26+D26 -> 22000 | F26: Korean PASS + RRN integration
A27: Insurance broker (in-transit + storage) | B27: 3000 | C27: 500 | D27: =C27*6 -> 3000 | E27: =B27+D27 -> 6000 | F27: Lloyds-syndicate-backed cover
A28: Korean inbound logistics partner | B28: 5000 | C28: 0 | D28: =C28*6 -> 0 | E28: =B28+D28 -> 5000 | F28: CJ Logistics or Lotte cross-border
A29: Subtotal | B29: =SUM(B22:B28) -> 278000 | C29: =SUM(C22:C28) -> 3700 | D29: =SUM(D22:D28) -> 22200 | E29: =SUM(E22:E28) -> 300200
A31: D. TECH PLATFORM BUILD
A32: Website + commerce build (front-end) | B32: 45000 | C32: 1500 | D32: =C32*6 -> 9000 | E32: =B32+D32 -> 54000 | F32: Vite React + headless commerce
A33: AGP backend (subscription + ledger) | B33: 55000 | C33: 2000 | D33: =C33*6 -> 12000 | E33: =B33+D33 -> 67000 | F33: Recurring billing + AUC ledger
A34: KYC + vault API integration | B34: 20000 | C34: 800 | D34: =C34*6 -> 4800 | E34: =B34+D34 -> 24800 | F34: PASS + Malca-Amit + ledger sync
A35: Spot price feed (Au/Ag + FX) | B35: 3000 | C35: 400 | D35: =C35*6 -> 2400 | E35: =B35+D35 -> 5400 | F35: Gold-API + Bloomberg FX
A36: Hosting + infra (Vercel/Supabase/AWS) | B36: 2000 | C36: 1500 | D36: =C36*6 -> 9000 | E36: =B36+D36 -> 11000 | F36: Multi-region, cold backup
A37: Security audit + pen-test (pre-launch) | B37: 12000 | C37: 0 | D37: =C37*6 -> 0 | E37: =B37+D37 -> 12000 | F37: OWASP top-10 + PII flow review
A38: Korean localization & translation | B38: 8000 | C38: 500 | D38: =C38*6 -> 3000 | E38: =B38+D38 -> 11000 | F38: Native Korean copy + maintenance
A39: Subtotal | B39: =SUM(B32:B38) -> 145000 | C39: =SUM(C32:C38) -> 6700 | D39: =SUM(D32:D38) -> 40200 | E39: =SUM(E32:E38) -> 185200
A41: E. MARKETING — 6-MONTH LAUNCH (linked to campaign tabs)
A42: Founders Plan launch (HNW dinners, video, PR) | B42: 35000 | C42: 8000 | D42: =C42*6 -> 48000 | E42: =B42+D42 -> 83000 | F42: Direct relationship building — highest-value
A43: AGP Sign-up campaign — paid mktg + gifts | B43: 0 | C43: ='17. AGP Sign-up — Inputs'!B19/6 -> 8333.3333 | D43: ='17. AGP Sign-up — Inputs'!B19 -> 50000 | E43: =B43+D43 -> 50000 | F43: Linked: Tab 11 paid mktg budget
A44: AGP acquisition (always-on paid) | B44: 0 | C44: ='15. AGP — Inputs'!B27 -> 10000 | D44: =C44*6 -> 60000 | E44: =B44+D44 -> 60000 | F44: Linked: Tab 9 monthly AGP acquisition
A45: Brand always-on (creative, content, social) | B45: 15000 | C45: ='4. Pricing Levers'!B34 -> 5000 | D45: =C45*6 -> 30000 | E45: =B45+D45 -> 45000 | F45: Linked: Pricing Levers personnel/brand row
A46: Korean PR agency (3-mo launch retainer) | B46: 18000 | C46: 0 | D46: =C46*6 -> 0 | E46: =B46+D46 -> 18000 | F46: Tech press, finance verticals, lifestyle
A47: Korean creator partnerships (10 mid-size) | B47: 20000 | C47: 8000 | D47: =C47*6 -> 48000 | E47: =B47+D47 -> 68000 | F47: 재테크 YouTubers + IG personalities
A48: Subtotal: Marketing Launch | B48: =SUM(B42:B47) -> 88000 | C48: =SUM(C42:C47) -> 39333.333 | D48: =SUM(D42:D47) -> 236000 | E48: =SUM(E42:E47) -> 324000
A50: F. PERSONNEL — FOUNDING TEAM (6 mo runway)
A51: CEO / Founder (Thomas) — partial salary | B51: 0 | C51: 6000 | D51: =C51*6 -> 36000 | E51: =B51+D51 -> 36000 | F51: Below market — equity-weighted
A52: CFO / Co-founder #2 — partial salary | B52: 0 | C52: 6000 | D52: =C52*6 -> 36000 | E52: =B52+D52 -> 36000 | F52: Singapore-based, FX + treasury
A53: GC/Compliance Co-founder #3 — partial sal | B53: 0 | C53: 5500 | D53: =C53*6 -> 33000 | E53: =B53+D53 -> 33000 | F53: PSPM + PIPA execution
A54: Head of Engineering (contractor → FT) | B54: 15000 | C54: 9000 | D54: =C54*6 -> 54000 | E54: =B54+D54 -> 69000 | F54: Korean-speaking pref
A55: Brand/Creative lead (contractor) | B55: 5000 | C55: 4500 | D55: =C55*6 -> 27000 | E55: =B55+D55 -> 32000 | F55: Korean native; fractional Y1 OK
A56: Operations / customer success (FT) | B56: 3000 | C56: 4000 | D56: =C56*6 -> 24000 | E56: =B56+D56 -> 27000 | F56: Korean native; Seoul or remote
A57: Payroll, EOR, benefits (Singapore) | B57: 4000 | C57: 1200 | D57: =C57*6 -> 7200 | E57: =B57+D57 -> 11200 | F57: Deel or Remote.com
A58: Subtotal | B58: =SUM(B51:B57) -> 27000 | C58: =SUM(C51:C57) -> 36200 | D58: =SUM(D51:D57) -> 217200 | E58: =SUM(E51:E57) -> 244200
A60: G. WORKING CAPITAL BUFFER & CONTINGENCY
A61: Inventory float top-up (months 4-6) | B61: 100000 | C61: 0 | D61: =C61*6 -> 0 | E61: =B61+D61 -> 100000 | F61: As order volume grows, more on-hand stock
A62: Refund / return reserve | B62: 20000 | C62: 0 | D62: =C62*6 -> 0 | E62: =B62+D62 -> 20000 | F62: 30-day refund policy on first orders
A63: FX hedging margin (USD/KRW/SGD) | B63: 15000 | C63: 0 | D63: =C63*6 -> 0 | E63: =B63+D63 -> 15000 | F63: Forward contracts to lock pricing
A64: Contingency (10% of A-F subtotals) | B64: =ROUND(0.1*(B11+B19+B29+B39+B48+B58),0) -> 63800 | C64: =ROUND(0.1*(C11+C19+C29+C39+C48+C58),0) -> 9473 | D64: =C64*6 -> 56838 | E64: =B64+D64 -> 120638 | F64: Recommended buffer for unknowns
A65: Subtotal: Working Capital | B65: =SUM(B61:B64) -> 198800 | C65: =SUM(C61:C64) -> 9473 | D65: =SUM(D61:D64) -> 56838 | E65: =SUM(E61:E64) -> 255638
A68: TOTAL CASH NEED — 6-MONTH RUNWAY BASELINE
A69: GRAND TOTAL — CASH REQUIRED TO LAUNCH | B69: =B11+B19+B29+B39+B48+B58+B65 -> 836800 | C69: =C11+C19+C29+C39+C48+C58+C65 -> 104206.33 | D69: =D11+D19+D29+D39+D48+D58+D65 -> 625238 | E69: =E11+E19+E29+E39+E48+E58+E65 -> 1462038
A72: RAISE STRUCTURE — RECOMMENDED
A73: Source | B73: Amount | C73: % of Raise | D73: Notes
A74: Founders own contribution (cash + sweat) | B74: =ROUND(E69*0.15,0) -> 219306 | C74: 0.15 | D74: Skin in the game — typical 10-20%
A75: Convertible note / SAFE — friends & family | B75: =ROUND(E69*0.2,0) -> 292408 | C75: 0.2 | D75: Bridge to seed; 6-12 mo conversion
A76: Seed round — institutional or HNW angels | B76: =ROUND(E69*0.65,0) -> 950325 | C76: 0.65 | D76: Priced round, 18-24 mo runway
A77: Total raise target | B77: =SUM(B74:B76) -> 1462039 | C77: =SUM(C74:C76) -> 1 | D77: Equals grand total above
A80: CHART: CASH NEED BY CATEGORY
A82: Category | B82: Total $
A83: Legal & Entity | B83: =E11 -> 34800
A84: Compliance | B84: =E19 -> 118000
A85: Vault & Vendors | B85: =E29 -> 300200
A86: Tech Platform | B86: =E39 -> 185200
A87: Marketing Launch | B87: =E48 -> 324000
A88: Personnel (6mo) | B88: =E58 -> 244200
A89: Working Capital | B89: =E65 -> 255638

Sheet 8. Equity Structure
A1: AURUM — EQUITY STRUCTURE & CAP TABLE | I1: ↑ P&L | P1: ↑ P&L
A2: Pre/post money cap table. 3 founders + ESOP + investor + lender placeholders. Edit yellow cells to model dilution.
A4: 1. VALUATION & ROUND INPUTS (edit yellow)
A5: Total cash needed (from Tab 14) | B5: ='7. Start-up Requirements'!E69 -> 1462038 | C5: Pulled from Start-up Requirements grand total
A6: % raised from priced equity round | B6: 0.25 | C6: Balance comes from founders + SAFE/note (Tab 14)
A7: Equity round size | B7: =B5*B6 -> 365509.5
A8: Pre-money valuation | B8: 20000000 | C8: Negotiated — 8M default for SG e-com early stage
A9: Post-money valuation | B9: =B8+B7 -> 20365510
A10: New investor ownership % | B10: =B7/B9 -> 0.017947476
A11: ESOP pool (post-money) | B11: 0.25 | C11: Standard 10% — comes out of pre-money
A12: Convertible note / SAFE amount (Tab 14) | B12: ='7. Start-up Requirements'!B74 -> 219306
A13: SAFE/note discount rate | B13: 0.2 | C13: 20% discount typical for friends & family bridge
A14: SAFE/note valuation cap | B14: 6000000 | C14: Conversion at lower of cap or discount
A15: SAFE conversion price (lower of cap/discount) | B15: =B12/MIN(B14,B8*(1-B13)) -> 0.036551
A17: 2. PRE-MONEY CAP TABLE — FOUNDERS
A18: Holder | B18: Role | C18: Shares | D18: Pre-money % | E18: Vesting | F18: Cliff | G18: Notes
A19: Thomas K. Jung | B19: CEO / Founder | C19: 3000000 | D19: =C19/SUM(C$19:C$22) -> 0.3 | E19: 4 yr | F19: 1 yr | G19: Equal partner — operator + CEO
A20: Jae Chung | B20: CFO / Treasury | C20: 3000000 | D20: =C20/SUM(C$19:C$22) -> 0.3 | E20: 4 yr | F20: 1 yr | G20: Equal partner — Singapore-based; FX + treasury
A21: Brian Lee | B21: GC / Compliance | C21: 3000000 | D21: =C21/SUM(C$19:C$22) -> 0.3 | E21: 4 yr | F21: 1 yr | G21: Equal partner — PSPM + PIPA execution
A22: ESOP Pool (unallocated) | B22: Reserve for hires | C22: 1000000 | D22: =C22/SUM(C$19:C$22) -> 0.1 | E22: — | F22: — | G22: Allocated to early hires
A23: TOTAL PRE-MONEY | B23: — | C23: =SUM(C19:C22) -> 10000000 | D23: =SUM(D19:D22) -> 1 | E23: — | F23: — | G23: — | H23: —
A26: 3. POST-MONEY CAP TABLE (after equity round + SAFE conversion)
A27: Holder | B27: Type | C27: Pre-Round % | D27: Dilution | E27: Post-Round % | F27: $ Value @ Post | G27: Notes
A28: Thomas K. Jung | B28: Founder | C28: =D19 -> 0.3 | D28: =C28*(B10+B15) -> 0.016349543 | E28: =C28-D28 -> 0.28365046 | F28: =E28*B9 -> 5776686.1 | G28: Diluted by new equity + SAFE conversion
A29: Jae Chung | B29: Founder | C29: =D20 -> 0.3 | D29: =C29*(B10+B15) -> 0.016349543 | E29: =C29-D29 -> 0.28365046 | F29: =E29*B9 -> 5776686.1 | G29: Diluted by new equity + SAFE conversion
A30: Brian Lee | B30: Founder | C30: =D21 -> 0.3 | D30: =C30*(B10+B15) -> 0.016349543 | E30: =C30-D30 -> 0.28365046 | F30: =E30*B9 -> 5776686.1 | G30: Diluted by new equity + SAFE conversion
A31: ESOP Pool | B31: Reserve | C31: =D22 -> 0.1 | D31: =C31*(B10+B15) -> 0.0054498476 | E31: =C31-D31 -> 0.094550152 | F31: =E31*B9 -> 1925562 | G31: Diluted by new equity + SAFE conversion
A32: SAFE/Note holders (F&F bridge) | B32: Convertible | C32: 0 | D32: 0 | E32: =B15 -> 0.036551 | F32: =E32*B9 -> 744379.74 | G32: Converts at lower of cap or discount
A33: New Investors (Seed Round) | B33: Equity | C33: 0 | D33: 0 | E33: =B10 -> 0.017947476 | F33: =E33*B9 -> 365509.5 | G33: Investment: =7 cell
A34: Lender (debt — non-dilutive placeholder) | B34: Debt | C34: 0 | D34: 0 | E34: 0 | F34: 0 | G34: Inventory financing line — separate from cap table
A35: TOTAL POST-MONEY | B35: — | C35: =SUM(C28:C34) -> 1 | D35: =SUM(D28:D34) -> 0.054498476 | E35: =SUM(E28:E34) -> 1 | F35: =SUM(F28:F34) -> 20365509 | G35: Total ownership = 100%
A38: 4. SCENARIO — SERIES A DILUTION PREVIEW (12-18 months out)
A39: Lever | B39: Value | C39: Notes
A40: Series A round size | B40: 4000000 | C40: Typical Series A for SG fintech/e-com
A41: Series A pre-money valuation | B41: 25000000 | C41: Assumes ~3x multiple on seed post-money
A42: Series A new ownership % | B42: =B40/(B41+B40) -> 0.13793103 | C42: Dilution to all existing holders
A43: Founder Thomas — fully diluted ownership after Series A | B43: =E28*(1-B42) -> 0.24452626 | C43: =B43*B9*(B41+B40)/B9 -> 7091261.4 | D43: $ value at Series A post-money
A44: All founders combined — fully diluted after Series A | B44: =(E28+E29+E30)*(1-B42) -> 0.73357877 | C44: =B44*(B41+B40) -> 21273784 | D44: Founders should hold >50% post-Series A for control
A47: 5. POST-MONEY OWNERSHIP (chart)
A49: Holder | B49: Post-Money %
A50: Thomas K. Jung | B50: =E28 -> 0.28365046
A51: Co-Founder #2 | B51: =E29 -> 0.28365046
A52: Co-Founder #3 | B52: =E30 -> 0.28365046
A53: ESOP Pool | B53: =E31 -> 0.094550152
A54: SAFE Holders | B54: =E32 -> 0.036551
A55: New Investors | B55: =E33 -> 0.017947476

Sheet 9. Balance Sheet
A1: AURUM — BALANCE SHEET (5-YEAR ANNUAL) | I1: ↑ P&L | P1: ↑ P&L
A2: P&L driven. Initial outlay from Tab 14. Cash builds from EBITDA. Inventory grows with customer base. Equity from Tab 15.
A4: Line Item | B4: Initial | C4: Y1 | D4: Y2 | E4: Y3 | F4: Y4 | G4: Y5 | H4: Notes
A5: ASSETS
A6: Cash & equivalents | B6: ='10. Cash Flow'!B31 -> 133714 | C6: ='10. Cash Flow'!C31 -> 2188468.8 | D6: ='10. Cash Flow'!D31 -> 11690587 | E6: ='10. Cash Flow'!E31 -> 20012352 | F6: ='10. Cash Flow'!F31 -> 32351070 | G6: ='10. Cash Flow'!G31 -> 47993195 | H6: Linked to Cash Flow tab ending cash balance
A7: Inventory — Working float (Aurum-owned) | B7: ='7. Start-up Requirements'!B23+'7. Start-up Requirements'!B24 -> 210000 | C7: =B7+'7. Start-up Requirements'!B57 -> 214000 | D7: =C7*1.3 -> 278200 | E7: =D7*1.2 -> 333840 | F7: =E7*1.15 -> 383916 | G7: =F7*1.1 -> 422307.6 | H7: Aurum-owned working stock; not customer-allocated
A8: Inventory — Customer-allocated (custodial) | B8: =B16 -> 0 | C8: =C16 -> 20687520 | D8: =D16 -> 41375040 | E8: =E16 -> 62062560 | F8: =F16 -> 86887584 | G8: =G16 -> 108609480 | H8: Custodial — fully reserved at vault. Mirrors customer deposit liability
A9: Accounts receivable | B9: 0 | C9: ='3. 5-Year Forecast'!B19*0.02 -> 61840.369 | D9: ='3. 5-Year Forecast'!C19*0.02 -> 147634.3 | E9: ='3. 5-Year Forecast'!D19*0.02 -> 221451.45 | F9: ='3. 5-Year Forecast'!E19*0.02 -> 327997.19 | G9: ='3. 5-Year Forecast'!F19*0.02 -> 423470.37 | H9: ~2% of revenue — most payments instant
A10: Prepaid expenses & deposits | B10: ='7. Start-up Requirements'!B22+'7. Start-up Requirements'!B26+'7. Start-up Requirements'!B33 -> 90000 | C10: =B10 -> 90000 | D10: =B10 -> 90000 | E10: =B10 -> 90000 | F10: =B10 -> 90000 | G10: =B10 -> 90000 | H10: Vault deposit + KYC vendor + insurance escrow
A11: Tech platform (capitalized, net of amort) | B11: ='7. Start-up Requirements'!B33+'7. Start-up Requirements'!B34+'7. Start-up Requirements'!B35 -> 78000 | C11: =MAX(0,B11*(1-(1/3))) -> 52000 | D11: =MAX(0,B11*(1-(2/3))) -> 26000 | E11: =MAX(0,B11*(1-(3/3))) -> 0 | F11: =MAX(0,B11*(1-(4/3))) -> 0 | G11: =MAX(0,B11*(1-(5/3))) -> 0 | H11: 3-year straight-line amortization
A12: TOTAL ASSETS | B12: =SUM(B6:B11) -> 511714 | C12: =SUM(C6:C11) -> 23293829 | D12: =SUM(D6:D11) -> 53607461 | E12: =SUM(E6:E11) -> 82720203 | F12: =SUM(F6:F11) -> 1.2004057e+08 | G12: =SUM(G6:G11) -> 1.5753845e+08 | H12: Sum of all assets
A15: LIABILITIES
A16: Customer deposits — physical AUC | B16: 0 | C16: ='13. Founders — Aggregate'!C11*'13. Founders — Aggregate'!F11+'16. AGP — Math'!F27 -> 20687520 | D16: =C16*'3. 5-Year Forecast'!B6 -> 41375040 | E16: =D16*'3. 5-Year Forecast'!C6 -> 62062560 | F16: =E16*'3. 5-Year Forecast'!D6 -> 86887584 | G16: =F16*'3. 5-Year Forecast'!E6 -> 108609480 | H16: Customer-owned physical metal — fully reserved at vault
A17: Accrued expenses | B17: 0 | C17: ='3. 5-Year Forecast'!B27/12 -> 43820.833 | D17: ='3. 5-Year Forecast'!C27/12 -> 64151.25 | E17: ='3. 5-Year Forecast'!D27/12 -> 91802.875 | F17: ='3. 5-Year Forecast'!E27/12 -> 131953.11 | G17: ='3. 5-Year Forecast'!F27/12 -> 190453.11 | H17: ~1 month indirect cost accrual
A18: SAFE / Convertible note (pre-conversion) | B18: ='8. Equity Structure'!B12 -> 219306 | C18: 0 | D18: 0 | E18: 0 | F18: 0 | G18: 0 | H18: Converts to equity by end of Y1
A19: TOTAL LIABILITIES | B19: =SUM(B16:B18) -> 219306 | C19: =SUM(C16:C18) -> 20731341 | D19: =SUM(D16:D18) -> 41439191 | E19: =SUM(E16:E18) -> 62154363 | F19: =SUM(F16:F18) -> 87019537 | G19: =SUM(G16:G18) -> 1.0879993e+08
A22: EQUITY
A23: Paid-in capital — Founders | B23: ='7. Start-up Requirements'!B73 -> Amount | C23: =B23 -> Amount | D23: =B23 -> Amount | E23: =B23 -> Amount | F23: =B23 -> Amount | G23: =B23 -> Amount | H23: Founder cash contribution
A24: Paid-in capital — Investors (Seed) | B24: ='7. Start-up Requirements'!B75 -> 292408 | C24: =B24 -> 292408 | D24: =B24 -> 292408 | E24: =B24 -> 292408 | F24: =B24 -> 292408 | G24: =B24 -> 292408 | H24: Seed round proceeds
A25: Paid-in capital — SAFE conversion (Y1) | B25: 0 | C25: ='7. Start-up Requirements'!B74 -> 219306 | D25: =C25 -> 219306 | E25: =C25 -> 219306 | F25: =C25 -> 219306 | G25: =C25 -> 219306 | H25: Note converts to equity in Y1
A26: Retained earnings (cumulative EBITDA) | B26: 0 | C26: ='3. 5-Year Forecast'!B31 -> 2110595.2 | D26: ='3. 5-Year Forecast'!C31 -> 7748707.3 | E26: ='3. 5-Year Forecast'!D31 -> 16185929 | F26: ='3. 5-Year Forecast'!E31 -> 28667269 | G26: ='3. 5-Year Forecast'!F31 -> 44429259 | H26: Cumulative EBITDA from 5Y forecast
A27: TOTAL EQUITY | B27: =SUM(B23:B26) -> 292408 | C27: =SUM(C23:C26) -> 2622309.2 | D27: =SUM(D23:D26) -> 8260421.3 | E27: =SUM(E23:E26) -> 16697643 | F27: =SUM(F23:F26) -> 29178983 | G27: =SUM(G23:G26) -> 44940973
A29: TOTAL LIABILITIES + EQUITY | B29: =B19+B27 -> 511714 | C29: =C19+C27 -> 23353650 | D29: =D19+D27 -> 49699613 | E29: =E19+E27 -> 78852006 | F29: =F19+F27 -> 1.1619852e+08 | G29: =G19+G27 -> 1.5374091e+08 | H29: Should reconcile to Total Assets
A31: Check: Assets - (L+E) | B31: =B12-B29 -> 0 | C31: =C12-C29 -> -59820.833 | D31: =D12-D29 -> 3907848.7 | E31: =E12-E29 -> 3868197.1 | F31: =F12-F29 -> 3842046.9 | G31: =G12-G29 -> 3797546.9 | H31: Should be ~0; small differences from inventory growth assumption
A34: KEY BALANCE SHEET RATIOS
A35: Cash runway (months at Y1 burn) | C35: =IF('3. 5-Year Forecast'!B29<0,B6/(-'3. 5-Year Forecast'!B29/12),"∞") -> ∞ | D35: =IF('3. 5-Year Forecast'!C29<0,C6/(-'3. 5-Year Forecast'!C29/12),"∞") -> ∞ | E35: =IF('3. 5-Year Forecast'!D29<0,D6/(-'3. 5-Year Forecast'!D29/12),"∞") -> ∞ | F35: =IF('3. 5-Year Forecast'!E29<0,E6/(-'3. 5-Year Forecast'!E29/12),"∞") -> ∞ | G35: =IF('3. 5-Year Forecast'!F29<0,F6/(-'3. 5-Year Forecast'!F29/12),"∞") -> ∞ | H35: Months of runway at current burn rate
A36: Equity ratio (Equity / Total Assets) | B36: =B27/B12 -> 0.57142857 | C36: =C27/C12 -> 0.11257527 | D36: =D27/D12 -> 0.15409089 | E36: =E27/E12 -> 0.20185689 | F36: =F27/F12 -> 0.24307602 | G36: =G27/G12 -> 0.28526986 | H36: Higher = stronger balance sheet
A37: Inventory turnover (Revenue / Avg Inv) | B37: — | C37: ='3. 5-Year Forecast'!B19/(C7+C8) -> 0.14793271 | D37: ='3. 5-Year Forecast'!C19/(D7+D8) -> 0.17721826 | E37: ='3. 5-Year Forecast'!D19/(E7+E8) -> 0.17745531 | F37: ='3. 5-Year Forecast'!E19/(F7+F8) -> 0.1879177 | G37: ='3. 5-Year Forecast'!F19/(G7+G8) -> 0.19419583 | H37: How fast inventory turns into revenue
A40: CHART: ASSETS / LIABILITIES / EQUITY OVER TIME
A42: Year | B42: Total Assets | C42: Total Liabilities | D42: Total Equity
A43: Initial | B43: =B12 -> 511714 | C43: =B19 -> 219306 | D43: =B27 -> 292408
A44: Y1 | B44: =C12 -> 23293829 | C44: =C19 -> 20731341 | D44: =C27 -> 2622309.2
A45: Y2 | B45: =D12 -> 53607461 | C45: =D19 -> 41439191 | D45: =D27 -> 8260421.3
A46: Y3 | B46: =E12 -> 82720203 | C46: =E19 -> 62154363 | D46: =E27 -> 16697643
A47: Y4 | B47: =F12 -> 1.2004057e+08 | C47: =F19 -> 87019537 | D47: =F27 -> 29178983
A48: Y5 | B48: =G12 -> 1.5753845e+08 | C48: =G19 -> 1.0879993e+08 | D48: =G27 -> 44940973

Sheet 10. Cash Flow
A1: AURUM — CASH FLOW STATEMENT (5-YEAR ANNUAL) | I1: ↑ P&L | P1: ↑ P&L
A2: Operating + Investing + Financing. Pre-launch initial outlay shown separately. Negative cash signals raise need.
A4: Line Item | B4: Initial | C4: Y1 | D4: Y2 | E4: Y3 | F4: Y4 | G4: Y5 | H4: Notes
A5: BEGINNING CASH
A6: Beginning cash balance | B6: 0 | C6: =B31 -> 133714 | D6: =C31 -> 2188468.8 | E6: =D31 -> 11690587 | F6: =E31 -> 20012352 | G6: =F31 -> 32351070 | H6: Each year begins where prior year ended
A8: OPERATING ACTIVITIES
A9: EBITDA (from 5Y P&L) | B9: 0 | C9: ='3. 5-Year Forecast'!B29 -> 2110595.2 | D9: ='3. 5-Year Forecast'!C29 -> 5638112.1 | E9: ='3. 5-Year Forecast'!D29 -> 8437222 | F9: ='3. 5-Year Forecast'!E29 -> 12481340 | G9: ='3. 5-Year Forecast'!F29 -> 15761990 | H9: Net Contribution from 5Y forecast
A10: + Depreciation & amortization addback | B10: 0 | C10: =ROUND(('7. Start-up Requirements'!B33+'7. Start-up Requirements'!B34+'7. Start-up Requirements'!B35)/3,0) -> 26000 | D10: =ROUND(('7. Start-up Requirements'!B33+'7. Start-up Requirements'!B34+'7. Start-up Requirements'!B35)/3,0) -> 26000 | E10: =ROUND(('7. Start-up Requirements'!B33+'7. Start-up Requirements'!B34+'7. Start-up Requirements'!B35)/3,0) -> 26000 | F10: =ROUND(('7. Start-up Requirements'!B33+'7. Start-up Requirements'!B34+'7. Start-up Requirements'!B35)/3,0) -> 26000 | G10: =ROUND(('7. Start-up Requirements'!B33+'7. Start-up Requirements'!B34+'7. Start-up Requirements'!B35)/3,0) -> 26000 | H10: Tech platform 3-year straight-line amort
A11: - Increase in working inventory (Aurum-owned) | B11: 0 | C11: =-((('9. Balance Sheet'!C7)-('9. Balance Sheet'!B7))) -> -4000 | D11: =-((('9. Balance Sheet'!D7)-('9. Balance Sheet'!C7))) -> -64200 | E11: =-((('9. Balance Sheet'!E7)-('9. Balance Sheet'!D7))) -> -55640 | F11: =-((('9. Balance Sheet'!F7)-('9. Balance Sheet'!E7))) -> -50076 | G11: =-((('9. Balance Sheet'!G7)-('9. Balance Sheet'!F7))) -> -38391.6 | H11: Only working float — customer-allocated metal is custodial
A12: + Increase in customer deposits (custodial — offsets) | B12: 0 | C12: 0 | D12: 0 | E12: 0 | F12: 0 | G12: 0 | H12: Custodial flows offset between BS asset (inventory) + liability (deposit)
A13: - Increase in receivables / WC items | B13: 0 | C13: =-('3. 5-Year Forecast'!B19*0.02) -> -61840.369 | D13: =-(('3. 5-Year Forecast'!C19-'3. 5-Year Forecast'!B19)*0.02) -> -85793.929 | E13: =-(('3. 5-Year Forecast'!D19-'3. 5-Year Forecast'!C19)*0.02) -> -73817.149 | F13: =-(('3. 5-Year Forecast'!E19-'3. 5-Year Forecast'!D19)*0.02) -> -106545.75 | G13: =-(('3. 5-Year Forecast'!F19-'3. 5-Year Forecast'!E19)*0.02) -> -95473.176 | H13: AR ~2% of incremental revenue
A14: Net cash from operating activities | B14: =SUM(B9:B13) -> 0 | C14: =SUM(C9:C13) -> 2070754.8 | D14: =SUM(D9:D13) -> 5514118.1 | E14: =SUM(E9:E13) -> 8333764.9 | F14: =SUM(F9:F13) -> 12350718 | G14: =SUM(G9:G13) -> 15654125
A16: INVESTING ACTIVITIES
A17: - Tech platform build (capitalized) | B17: =-('7. Start-up Requirements'!B33+'7. Start-up Requirements'!B34+'7. Start-up Requirements'!B35) -> -78000 | C17: =-'7. Start-up Requirements'!C33*12*0.5 -> -12000 | D17: =-'7. Start-up Requirements'!C33*12*0.5 -> -12000 | E17: =-'7. Start-up Requirements'!C33*12*0.5 -> -12000 | F17: =-'7. Start-up Requirements'!C33*12*0.5 -> -12000 | G17: =-'7. Start-up Requirements'!C33*12*0.5 -> -12000 | H17: Initial build + ongoing capitalized improvements
A18: - Vault & vendor deposits | B18: =-('7. Start-up Requirements'!B22+'7. Start-up Requirements'!B26+'7. Start-up Requirements'!B33) -> -90000 | C18: 0 | D18: 0 | E18: 0 | F18: 0 | G18: 0 | H18: One-time vault deposit + KYC + insurance setup
A19: - Initial inventory float (Au + Ag) | B19: =-('7. Start-up Requirements'!B23+'7. Start-up Requirements'!B24) -> -210000 | C19: =-'7. Start-up Requirements'!B57 -> -4000 | D19: 0 | E19: 0 | F19: 0 | G19: 0 | H19: Initial gold + silver working float
A20: Net cash from investing activities | B20: =SUM(B17:B19) -> -378000 | C20: =SUM(C17:C19) -> -16000 | D20: =SUM(D17:D19) -> -12000 | E20: =SUM(E17:E19) -> -12000 | F20: =SUM(F17:F19) -> -12000 | G20: =SUM(G17:G19) -> -12000
A22: FINANCING ACTIVITIES
A23: + Founders contribution | B23: ='7. Start-up Requirements'!B73 -> Amount | C23: 0 | D23: 0 | E23: 0 | F23: 0 | G23: 0 | H23: Founder cash at incorporation
A24: + SAFE/Note proceeds (F&F bridge) | B24: ='7. Start-up Requirements'!B74 -> 219306 | C24: 0 | D24: 0 | E24: 0 | F24: 0 | G24: 0 | H24: Bridge financing — converts in Y1
A25: + Seed equity round proceeds | B25: ='7. Start-up Requirements'!B75 -> 292408 | C25: 0 | D25: 0 | E25: 0 | F25: 0 | G25: 0 | H25: Priced equity round at incorporation
A26: + Series A (modeled in Y2) | B26: 0 | C26: 0 | D26: ='8. Equity Structure'!B40 -> 4000000 | E26: 0 | F26: 0 | G26: 0 | H26: Series A injection — see Tab 15 scenario
A27: Net cash from financing activities | B27: =SUM(B23:B26) -> 511714 | C27: =SUM(C23:C26) -> 0 | D27: =SUM(D23:D26) -> 4000000 | E27: =SUM(E23:E26) -> 0 | F27: =SUM(F23:F26) -> 0 | G27: =SUM(G23:G26) -> 0
A29: ENDING CASH
A30: Net change in cash | B30: =B14+B20+B27 -> 133714 | C30: =C14+C20+C27 -> 2054754.8 | D30: =D14+D20+D27 -> 9502118.1 | E30: =E14+E20+E27 -> 8321764.9 | F30: =F14+F20+F27 -> 12338718 | G30: =G14+G20+G27 -> 15642125
A31: ENDING CASH BALANCE | B31: =B6+B30 -> 133714 | C31: =C6+C30 -> 2188468.8 | D31: =D6+D30 -> 11690587 | E31: =E6+E30 -> 20012352 | F31: =F6+F30 -> 32351070 | G31: =G6+G30 -> 47993195
A34: KEY CASH FLOW METRICS
A35: Free cash flow (Op CF + Investing) | B35: =B14+B20 -> -378000 | C35: =C14+C20 -> 2054754.8 | D35: =D14+D20 -> 5502118.1 | E35: =E14+E20 -> 8321764.9 | F35: =F14+F20 -> 12338718 | G35: =G14+G20 -> 15642125 | H35: Cash generated for shareholders/reinvestment
A36: FCF margin | B36: — | C36: =IFERROR(C35/'3. 5-Year Forecast'!B19,0) -> 0.66453511 | D36: =IFERROR(D35/'3. 5-Year Forecast'!C19,0) -> 0.74537126 | E36: =IFERROR(E35/'3. 5-Year Forecast'!D19,0) -> 0.75156564 | F36: =IFERROR(F35/'3. 5-Year Forecast'!E19,0) -> 0.75236731 | G36: =IFERROR(G35/'3. 5-Year Forecast'!F19,0) -> 0.73875889 | H36: FCF as % of revenue — investor focus metric
A37: Cash zero crossing (cumulative) | B37: =B31 -> 133714 | C37: =C31 -> 2188468.8 | D37: =D31 -> 11690587 | E37: =E31 -> 20012352 | F37: =F31 -> 32351070 | G37: =G31 -> 47993195 | H37: When does cash go positive on cumulative basis
A40: CHART: CASH BALANCE & FREE CASH FLOW
A42: Year | B42: Ending Cash | C42: Free Cash Flow
A43: Initial | B43: =B31 -> 133714 | C43: =B35 -> -378000
A44: Y1 | B44: =C31 -> 2188468.8 | C44: =C35 -> 2054754.8
A45: Y2 | B45: =D31 -> 11690587 | C45: =D35 -> 5502118.1
A46: Y3 | B46: =E31 -> 20012352 | C46: =E35 -> 8321764.9
A47: Y4 | B47: =F31 -> 32351070 | C47: =F35 -> 12338718
A48: Y5 | B48: =G31 -> 47993195 | C48: =G35 -> 15642125

Sheet 11. Founders — Inputs
A1: FOUNDERS PROGRAM (PHYSICAL) — INPUTS | I1: ↑ P&L | P1: ↑ P&L
A2: Founder Savings referral program for physical bullion. All in USD.
A4: VOLUME INPUTS — CUSTOMER BASE
A5: M6 customer base (target physical customers) | B5: 2000 | C5: Per launch strategy v2
A6: Avg young stacker ARR (USD) | B6: 2000 | C6: ~₩200K-300K/month annualized
A7: Avg HNW patron ARR (USD) | B7: 12000 | C7: Founding 500 / Patron tier
A8: % of customers who refer at all | B8: 0.3 | C8: Industry typical fintech
A10: → Total active physical customers | B10: =B5 -> 2000
A12: GATE STRUCTURE — 5 GATES (GMV-attributed thresholds)
A13: Gate | B13: KR Name | C13: GMV Threshold ($) | D13: Founder Savings % | E13: Reach % of base | F13: Notes
A14: I | B14: 시작의 문 | C14: 5000 | D14: 0.01 | E14: 0.25 | F14: Entry — ~2-3 referrals
A15: II | B15: 셋의 표식 | C15: 15000 | D15: 0.015 | E15: 0.08 | F15: 5-7 referrals · stainless mark
A16: III | B16: 정점 | C16: 35000 | D16: 0.02 | E16: 0.02 | F16: 12-15 refs · 10K SOLID GOLD MARK · Patron status
A17: IV | B17: 볼트 순례 | C17: 65000 | D17: 0.025 | E17: 0.005 | F17: 25+ refs · Singapore Vault Weekend
A18: V | B18: 평생의 표식 | C18: 100000 | D18: 0.03 | E18: 0.001 | F18: 40+ refs OR HNW · LIFETIME (rare; ECONOMIC APEX)
A21: AVG REFERRER OWN ARR BY GATE (USD)
A22: Gate | B22: Own ARR Assumption | C22: Logic
A23: I | B23: 2500 | C23: Lightly active referrer ≈ avg young stacker
A24: II | B24: 3500 | C24: Slightly elevated — engaged sharer
A25: III | B25: 7500 | C25: Power user / micro-influencer
A26: IV | B26: 15000 | C26: HNW connector or big stacker
A27: V | B27: 25000 | C27: True evangelist — likely HNW themselves

Sheet 12. Founders — Per-Patron
A1: FOUNDERS — PER-PATRON UNIT ECONOMICS | I1: ↑ P&L | P1: ↑ P&L
A2: For ONE Patron at each gate: cost vs gain. All USD.
A4: Gate | B4: KR Name | C4: Founder Savings | D4: Patron Own ARR | E4: Their Listed Price | F4: Annual Cost to Aurum | G4: Their Referred GMV | H4: Aurum Margin From Refs | I4: Net Aurum Value
A5: ='11. Founders — Inputs'!A14 -> I | B5: ='11. Founders — Inputs'!B14 -> 시작의 문 | C5: ='11. Founders — Inputs'!D14 -> 0.01 | D5: ='11. Founders — Inputs'!B23 -> 2500 | E5: =D5*(1+'4. Pricing Levers'!$B$12) -> 2737.5 | F5: =E5*C5 -> 27.375 | G5: ='11. Founders — Inputs'!C14 -> 5000 | H5: =G5*'4. Pricing Levers'!$B$12 -> 475 | I5: =H5-F5 -> 447.625
A6: ='11. Founders — Inputs'!A15 -> II | B6: ='11. Founders — Inputs'!B15 -> 셋의 표식 | C6: ='11. Founders — Inputs'!D15 -> 0.015 | D6: ='11. Founders — Inputs'!B24 -> 3500 | E6: =D6*(1+'4. Pricing Levers'!$B$12) -> 3832.5 | F6: =E6*C6 -> 57.4875 | G6: ='11. Founders — Inputs'!C15 -> 15000 | H6: =G6*'4. Pricing Levers'!$B$12 -> 1425 | I6: =H6-F6 -> 1367.5125
A7: ='11. Founders — Inputs'!A16 -> III | B7: ='11. Founders — Inputs'!B16 -> 정점 | C7: ='11. Founders — Inputs'!D16 -> 0.02 | D7: ='11. Founders — Inputs'!B25 -> 7500 | E7: =D7*(1+'4. Pricing Levers'!$B$12) -> 8212.5 | F7: =E7*C7 -> 164.25 | G7: ='11. Founders — Inputs'!C16 -> 35000 | H7: =G7*'4. Pricing Levers'!$B$12 -> 3325 | I7: =H7-F7 -> 3160.75
A8: ='11. Founders — Inputs'!A17 -> IV | B8: ='11. Founders — Inputs'!B17 -> 볼트 순례 | C8: ='11. Founders — Inputs'!D17 -> 0.025 | D8: ='11. Founders — Inputs'!B26 -> 15000 | E8: =D8*(1+'4. Pricing Levers'!$B$12) -> 16425 | F8: =E8*C8 -> 410.625 | G8: ='11. Founders — Inputs'!C17 -> 65000 | H8: =G8*'4. Pricing Levers'!$B$12 -> 6175 | I8: =H8-F8 -> 5764.375
A9: ='11. Founders — Inputs'!A18 -> V | B9: ='11. Founders — Inputs'!B18 -> 평생의 표식 | C9: ='11. Founders — Inputs'!D18 -> 0.03 | D9: ='11. Founders — Inputs'!B27 -> 25000 | E9: =D9*(1+'4. Pricing Levers'!$B$12) -> 27375 | F9: =E9*C9 -> 821.25 | G9: ='11. Founders — Inputs'!C18 -> 100000 | H9: =G9*'4. Pricing Levers'!$B$12 -> 9500 | I9: =H9-F9 -> 8678.75

Sheet 13. Founders — Aggregate
A1: FOUNDERS — AGGREGATE ECONOMICS | I1: ↑ P&L | P1: ↑ P&L
A2: Per-Patron numbers × Patrons reaching each gate. Annualized.
A4: Gate | B4: Reach % | C4: Patrons | D4: Annual Cost / Patron | E4: Total Annual Cost | F4: Inbound Margin / Patron | G4: Total Inbound Margin | H4: Net Program Value
A5: ='11. Founders — Inputs'!A14 -> I | B5: ='11. Founders — Inputs'!E14 -> 0.25 | C5: =ROUND('11. Founders — Inputs'!$B$5*B5,0) -> 500 | D5: ='12. Founders — Per-Patron'!F5 -> 27.375 | E5: =C5*D5 -> 13687.5 | F5: ='12. Founders — Per-Patron'!H5 -> 475 | G5: =C5*F5 -> 237500 | H5: =G5-E5 -> 223812.5
A6: ='11. Founders — Inputs'!A15 -> II | B6: ='11. Founders — Inputs'!E15 -> 0.08 | C6: =ROUND('11. Founders — Inputs'!$B$5*B6,0) -> 160 | D6: ='12. Founders — Per-Patron'!F6 -> 57.4875 | E6: =C6*D6 -> 9198 | F6: ='12. Founders — Per-Patron'!H6 -> 1425 | G6: =C6*F6 -> 228000 | H6: =G6-E6 -> 218802
A7: ='11. Founders — Inputs'!A16 -> III | B7: ='11. Founders — Inputs'!E16 -> 0.02 | C7: =ROUND('11. Founders — Inputs'!$B$5*B7,0) -> 40 | D7: ='12. Founders — Per-Patron'!F7 -> 164.25 | E7: =C7*D7 -> 6570 | F7: ='12. Founders — Per-Patron'!H7 -> 3325 | G7: =C7*F7 -> 133000 | H7: =G7-E7 -> 126430
A8: ='11. Founders — Inputs'!A17 -> IV | B8: ='11. Founders — Inputs'!E17 -> 0.005 | C8: =ROUND('11. Founders — Inputs'!$B$5*B8,0) -> 10 | D8: ='12. Founders — Per-Patron'!F8 -> 410.625 | E8: =C8*D8 -> 4106.25 | F8: ='12. Founders — Per-Patron'!H8 -> 6175 | G8: =C8*F8 -> 61750 | H8: =G8-E8 -> 57643.75
A9: ='11. Founders — Inputs'!A18 -> V | B9: ='11. Founders — Inputs'!E18 -> 0.001 | C9: =ROUND('11. Founders — Inputs'!$B$5*B9,0) -> 2 | D9: ='12. Founders — Per-Patron'!F9 -> 821.25 | E9: =C9*D9 -> 1642.5 | F9: ='12. Founders — Per-Patron'!H9 -> 9500 | G9: =C9*F9 -> 19000 | H9: =G9-E9 -> 17357.5
A11: TOTAL | C11: =SUM(C5:C9) -> 712 | E11: =SUM(E5:E9) -> 35204.25 | G11: =SUM(G5:G9) -> 679250 | H11: =SUM(H5:H9) -> 644045.75

Sheet 14. Founders — Sensitivity
A1: FOUNDERS — SENSITIVITY | I1: ↑ P&L | P1: ↑ P&L
A4: SCENARIO 1 — REACH MULTIPLIER (premium held at base)
A5: Scenario | B5: Reach Mult | C5: Patrons | D5: Cost | E5: Margin | F5: Net | G5: ROI
A6: Bearish | B6: 0.5 | C6: =ROUND('13. Founders — Aggregate'!C11*B6,0) -> 356 | D6: ='13. Founders — Aggregate'!E11*B6 -> 17602.125 | E6: ='13. Founders — Aggregate'!G11*B6 -> 339625 | F6: =E6-D6 -> 322022.88 | G6: =E6/D6 -> 19.294545
A7: Base case | B7: 1 | C7: =ROUND('13. Founders — Aggregate'!C11*B7,0) -> 712 | D7: ='13. Founders — Aggregate'!E11*B7 -> 35204.25 | E7: ='13. Founders — Aggregate'!G11*B7 -> 679250 | F7: =E7-D7 -> 644045.75 | G7: =E7/D7 -> 19.294545
A8: Bullish | B8: 2 | C8: =ROUND('13. Founders — Aggregate'!C11*B8,0) -> 1424 | D8: ='13. Founders — Aggregate'!E11*B8 -> 70408.5 | E8: ='13. Founders — Aggregate'!G11*B8 -> 1358500 | F8: =E8-D8 -> 1288091.5 | G8: =E8/D8 -> 19.294545
A9: Viral | B9: 3 | C9: =ROUND('13. Founders — Aggregate'!C11*B9,0) -> 2136 | D9: ='13. Founders — Aggregate'!E11*B9 -> 105612.75 | E9: ='13. Founders — Aggregate'!G11*B9 -> 2037750 | F9: =E9-D9 -> 1932137.2 | G9: =E9/D9 -> 19.294545
A10: Saturation | B10: 5 | C10: =ROUND('13. Founders — Aggregate'!C11*B10,0) -> 3560 | D10: ='13. Founders — Aggregate'!E11*B10 -> 176021.25 | E10: ='13. Founders — Aggregate'!G11*B10 -> 3396250 | F10: =E10-D10 -> 3220228.8 | G10: =E10/D10 -> 19.294545

Sheet 15. AGP — Inputs
A1: AURUM GOLD PLAN (AGP) — INPUTS | I1: ↑ P&L | P1: ↑ P&L
A2: Standalone savings program. 12-month auto-debit commitment. AGP customer base = funnel-driven + sign-up campaign-driven.
A4: AGP TIERS — MONTHLY CONTRIBUTION
A5: Tier | B5: Tier Name | C5: Monthly USD | D5: Annual USD | E5: Mix % of base | F5: Notes
A6: Bronze | B6: 브론즈 | C6: 140 | D6: =C6*12 -> 1680 | E6: 0.4 | F6: Entry · ~₩200K/mo
A7: Silver | B7: 실버 | C7: 350 | D7: =C7*12 -> 4200 | E7: 0.3 | F7: Standard · ~₩500K/mo
A8: Gold | B8: 골드 | C8: 700 | D8: =C8*12 -> 8400 | E8: 0.25 | F8: Serious accumulator · ~₩1M/mo
A9: Platinum | B9: 플래티넘 | C9: 1700 | D9: =C9*12 -> 20400 | E9: 0.03 | F9: HNW recurring · ~₩2.5M/mo
A10: Sovereign | B10: 소브린 | C10: 3400 | D10: =C10*12 -> 40800 | E10: 0.02 | F10: Top-tier · ~₩5M/mo
B11: Weighted avg monthly per AGP customer | E11: =SUMPRODUCT(C6:C10,E6:E10) -> 455
A13: ORGANIC AGP FUNNEL — VOLUME INPUTS
A14: Metric | B14: Base | C14: Low | D14: High | E14: Unit | F14: Notes
A15: Marketing impressions per month | B15: 200000 | C15: 50000 | D15: 500000 | E15: count | F15: Combined paid + organic + KakaoTalk
A16: Click-through rate | B16: 0.025 | C16: 0.01 | D16: 0.05 | E16: % | F16: Korean fintech avg
A17: Sign-up conversion (clicks → signups) | B17: 0.08 | C17: 0.03 | D17: 0.15 | E17: % | F17: CTR-to-signup
A18: Activation rate (signup → 1st AGP debit) | B18: 0.45 | C18: 0.25 | D18: 0.65 | E18: % | F18: Biggest funnel leak
A19: AGP completion rate (12-month full term) | B19: 0.7 | C19: 0.5 | D19: 0.85 | E19: % | F19: Auto-debit boosts retention
A21: CHURN & RETENTION ASSUMPTIONS
A22: Monthly AGP churn rate (mid-program) | B22: 0.025 | C22: Auto-debit stickiness
A23: Annual AGP retention rate | B23: =POWER(1-B22,12) -> 0.73799835 | C23: (computed)
A24: Year 2+ AGP retention rate | B24: 0.65 | C24: After 12-mo term completes
A26: AGP MARKETING COST INPUTS
A27: Monthly marketing budget for organic AGP acquisition | B27: 10000 | C27: Direct AGP funnel
A28: Average CAC per AGP customer (target) | B28: 25 | C28: Referral-led keeps low

Sheet 16. AGP — Math
A1: AGP — FUNNEL & TIER GMV (organic + sign-up campaign) | I1: ↑ P&L | P1: ↑ P&L
A2: AGP customer base = Organic funnel + Sign-up campaign activations. Both flow into tier math.
A4: SOURCE 1 — ORGANIC FUNNEL (annualized)
A5: Stage | B5: Monthly | C5: Annual | D5: Conversion %
A6: Impressions | B6: ='15. AGP — Inputs'!B15 -> 200000 | C6: =B6*12 -> 2400000 | D6: —
A7: Clicks | B7: =B6*'15. AGP — Inputs'!B16 -> 5000 | C7: =B7*12 -> 60000 | D7: ='15. AGP — Inputs'!B16 -> 0.025
A8: Sign-ups | B8: =B7*'15. AGP — Inputs'!B17 -> 400 | C8: =B8*12 -> 4800 | D8: ='15. AGP — Inputs'!B17 -> 0.08
A9: Activated (1st debit) | B9: =B8*'15. AGP — Inputs'!B18 -> 180 | C9: =B9*12 -> 2160 | D9: ='15. AGP — Inputs'!B18 -> 0.45
A10: 12-mo completers | B10: =B9*'15. AGP — Inputs'!B19 -> 126 | C10: =B10*12 -> 1512 | D10: ='15. AGP — Inputs'!B19 -> 0.7
A12: SOURCE 2 — SIGN-UP CAMPAIGN (one-time boost)
A13: Sign-up campaign AGP-activated customers | D13: ='18. AGP Sign-up — Math'!C18 -> 1625 | E13: From sign-up campaign activation
A15: COMBINED ACTIVE AGP CUSTOMER BASE
A16: Active AGP customers (Organic + Sign-up) | D16: =C9+D13 -> 3785
A19: AGP GMV BY TIER (annual, USD)
A20: Tier | B20: Mix % | C20: Active customers | D20: Monthly contribution | E20: Annual GMV/customer | F20: Total annual GMV | G20: Aurum margin | H20: Storage rev
A21: ='15. AGP — Inputs'!A6 -> Bronze | B21: ='15. AGP — Inputs'!E6 -> 0.4 | C21: =ROUND($D$16*B21,0) -> 1514 | D21: ='15. AGP — Inputs'!C6 -> 140 | E21: =D21*12 -> 1680 | F21: =C21*E21 -> 2543520 | G21: =F21*'4. Pricing Levers'!$B$12 -> 241634.4 | H21: =F21*'4. Pricing Levers'!$B$16/2 -> 6358.8
A22: ='15. AGP — Inputs'!A7 -> Silver | B22: ='15. AGP — Inputs'!E7 -> 0.3 | C22: =ROUND($D$16*B22,0) -> 1136 | D22: ='15. AGP — Inputs'!C7 -> 350 | E22: =D22*12 -> 4200 | F22: =C22*E22 -> 4771200 | G22: =F22*'4. Pricing Levers'!$B$12 -> 453264 | H22: =F22*'4. Pricing Levers'!$B$16/2 -> 11928
A23: ='15. AGP — Inputs'!A8 -> Gold | B23: ='15. AGP — Inputs'!E8 -> 0.25 | C23: =ROUND($D$16*B23,0) -> 946 | D23: ='15. AGP — Inputs'!C8 -> 700 | E23: =D23*12 -> 8400 | F23: =C23*E23 -> 7946400 | G23: =F23*'4. Pricing Levers'!$B$12 -> 754908 | H23: =F23*'4. Pricing Levers'!$B$16/2 -> 19866
A24: ='15. AGP — Inputs'!A9 -> Platinum | B24: ='15. AGP — Inputs'!E9 -> 0.03 | C24: =ROUND($D$16*B24,0) -> 114 | D24: ='15. AGP — Inputs'!C9 -> 1700 | E24: =D24*12 -> 20400 | F24: =C24*E24 -> 2325600 | G24: =F24*'4. Pricing Levers'!$B$12 -> 220932 | H24: =F24*'4. Pricing Levers'!$B$16/2 -> 5814
A25: ='15. AGP — Inputs'!A10 -> Sovereign | B25: ='15. AGP — Inputs'!E10 -> 0.02 | C25: =ROUND($D$16*B25,0) -> 76 | D25: ='15. AGP — Inputs'!C10 -> 3400 | E25: =D25*12 -> 40800 | F25: =C25*E25 -> 3100800 | G25: =F25*'4. Pricing Levers'!$B$12 -> 294576 | H25: =F25*'4. Pricing Levers'!$B$16/2 -> 7752
A27: TOTAL | C27: =SUM(C21:C25) -> 3786 | F27: =SUM(F21:F25) -> 20687520 | G27: =SUM(G21:G25) -> 1965314.4 | H27: =SUM(H21:H25) -> 51718.8

Sheet 17. AGP Sign-up — Inputs
A1: AGP SIGN-UP CAMPAIGN — INPUTS | I1: ↑ P&L | P1: ↑ P&L
A2: Founding Gift drives 12-month AGP enrollment. Activations roll into AGP Math Tab as a one-time boost.
A4: AGP SIGN-UP GIFT TIERS
A5: Tier | B5: AGP commitment | C5: Gift value (USD) | D5: Mix % of signups | E5: Term (mo) | F5: Notes
A6: Trial | B6: 30-day AGP at $50/mo | C6: 5 | D6: 0.4 | E6: 1 | F6: Test the product · low commit
A7: Founding | B7: 12-mo AGP at $140/mo (Bronze) | C7: 30 | D7: 0.3 | E7: 12 | F7: Standard founding · ₩200K/mo
A8: Founding+ | B8: 12-mo AGP at $350/mo (Silver) | C8: 90 | D8: 0.25 | E8: 12 | F8: Mid-tier · ₩500K/mo
A9: Patron | B9: 12-mo AGP at $700/mo (Gold) | C9: 300 | D9: 0.03 | E9: 12 | F9: ₩1M/mo · concierge
A10: Sovereign | B10: 12-mo AGP at $1,700/mo (Plat) | C10: 1200 | D10: 0.02 | E10: 12 | F10: ₩2.5M/mo · 1-of-500 · 10K gold card
C11: Mix sum: | D11: =SUM(D6:D10) -> 1
B12: Weighted avg gift cost per signup | D12: =SUMPRODUCT(C6:C10,D6:D10) -> 66.5
A14: CAMPAIGN VOLUME & CONVERSION (controls Sign-up → AGP linkage)
A15: Metric | B15: Base | C15: Low | D15: High | E15: Unit | F15: Notes
A16: Total AGP signup target — 6-month campaign | B16: 2500 | C16: 1500 | D16: 12000 | E16: count | F16: M1-M6 cohort
A17: % Signups → AGP activation (1st debit) | B17: 0.65 | C17: 0.4 | D17: 0.85 | E17: % | F17: KEY LINK: drives AGP customer count on Tab 10
A18: % Signups → complete 12-mo term | B18: 0.55 | C18: 0.35 | D18: 0.75 | E18: % | F18: Sticky once auto-debit running
A19: Marketing spend — 6-mo campaign (USD) | B19: 50000 | C19: 50000 | D19: 300000 | E19: USD | F19: Founding push budget
A20: All-in CAC target per signup (USD) | B20: 20 | C20: 20 | D20: 100 | E20: USD | F20: Marketing + gift / signups

Sheet 18. AGP Sign-up — Math
A1: AGP SIGN-UP CAMPAIGN — TIER GMV & FUNNEL | I1: ↑ P&L | P1: ↑ P&L
A2: Per-tier AGP signups → activation → AGP customer count (feeds into AGP Math Tab 10).
A4: PER-TIER AGP SIGNUPS (6-MONTH CAMPAIGN)
A5: Tier | B5: Mix % | C5: Sign-ups | D5: Gift cost/signup | E5: Total gift cost | F5: AGP GMV/customer (12mo) | G5: Total AGP GMV | H5: Aurum margin
A6: ='17. AGP Sign-up — Inputs'!A6 -> Trial | B6: ='17. AGP Sign-up — Inputs'!D6 -> 0.4 | C6: =ROUND('17. AGP Sign-up — Inputs'!B16*B6,0) -> 1000 | D6: ='17. AGP Sign-up — Inputs'!C6 -> 5 | E6: =C6*D6 -> 5000 | F6: =50*1 -> 50 | G6: =C6*F6*'17. AGP Sign-up — Inputs'!$B$17 -> 32500 | H6: =G6*'4. Pricing Levers'!$B$12 -> 3087.5
A7: ='17. AGP Sign-up — Inputs'!A7 -> Founding | B7: ='17. AGP Sign-up — Inputs'!D7 -> 0.3 | C7: =ROUND('17. AGP Sign-up — Inputs'!B16*B7,0) -> 750 | D7: ='17. AGP Sign-up — Inputs'!C7 -> 30 | E7: =C7*D7 -> 22500 | F7: =140*12 -> 1680 | G7: =C7*F7*'17. AGP Sign-up — Inputs'!$B$17 -> 819000 | H7: =G7*'4. Pricing Levers'!$B$12 -> 77805
A8: ='17. AGP Sign-up — Inputs'!A8 -> Founding+ | B8: ='17. AGP Sign-up — Inputs'!D8 -> 0.25 | C8: =ROUND('17. AGP Sign-up — Inputs'!B16*B8,0) -> 625 | D8: ='17. AGP Sign-up — Inputs'!C8 -> 90 | E8: =C8*D8 -> 56250 | F8: =350*12 -> 4200 | G8: =C8*F8*'17. AGP Sign-up — Inputs'!$B$17 -> 1706250 | H8: =G8*'4. Pricing Levers'!$B$12 -> 162093.75
A9: ='17. AGP Sign-up — Inputs'!A9 -> Patron | B9: ='17. AGP Sign-up — Inputs'!D9 -> 0.03 | C9: =ROUND('17. AGP Sign-up — Inputs'!B16*B9,0) -> 75 | D9: ='17. AGP Sign-up — Inputs'!C9 -> 300 | E9: =C9*D9 -> 22500 | F9: =700*12 -> 8400 | G9: =C9*F9*'17. AGP Sign-up — Inputs'!$B$17 -> 409500 | H9: =G9*'4. Pricing Levers'!$B$12 -> 38902.5
A10: ='17. AGP Sign-up — Inputs'!A10 -> Sovereign | B10: ='17. AGP Sign-up — Inputs'!D10 -> 0.02 | C10: =ROUND('17. AGP Sign-up — Inputs'!B16*B10,0) -> 50 | D10: ='17. AGP Sign-up — Inputs'!C10 -> 1200 | E10: =C10*D10 -> 60000 | F10: =1700*12 -> 20400 | G10: =C10*F10*'17. AGP Sign-up — Inputs'!$B$17 -> 663000 | H10: =G10*'4. Pricing Levers'!$B$12 -> 62985
A12: TOTAL | C12: =SUM(C6:C10) -> 2500 | E12: =SUM(E6:E10) -> 166250 | G12: =SUM(G6:G10) -> 3630250 | H12: =SUM(H6:H10) -> 344873.75
A15: LINKAGE TO AGP MATH (Tab 10)
A16: Total AGP signups generated | C16: =C12 -> 2500
A17: × Activation rate | C17: ='17. AGP Sign-up — Inputs'!B17 -> 0.65
A18: Total AGP | C18: =ROUND(C16*C17,0) -> 1625
A21: CAMPAIGN NET CONTRIBUTION
A22: Metric | B22: Value
A23: Total AGP sign-ups generated | E23: =C12 -> 2500
A24: Total attributed AGP GMV (12-mo) | E24: =G12 -> 3630250
A25: Aurum margin from AGP GMV | E25: =H12 -> 344873.75
A26: Total gift cost | E26: =E12 -> 166250
A27: Marketing spend (6-mo) | E27: ='17. AGP Sign-up — Inputs'!B19 -> 50000
A28: All-in CAC per AGP signup | E28: =(E12+'17. AGP Sign-up — Inputs'!B19)/C12 -> 86.5
A29: CAMPAIGN NET VALUE | E29: =H12-E12-'17. AGP Sign-up — Inputs'!B19 -> 128623.75
A30: ROI multiple | E30: =H12/(E12+'17. AGP Sign-up — Inputs'!B19) -> 1.5947919
